Workbook
Name lstAnswers: SETTINGS!$G$2:$G$5
Name lstCount: SETTINGS!$E$2:$E$5
Name lstDifficulty: SETTINGS!$C$2:$C$5
Name lstGenCount: SETTINGS!$K$2:$K$6
Name lstGenDifficulty: SETTINGS!$I$2:$I$5
Name lstGenStyle: SETTINGS!$O$2:$O$5
Name lstGenType: SETTINGS!$M$2:$M$3
Name lstSubjects: SETTINGS!$A$2:$A$11

Sheet HOME
A1: EXCEL AI STUDY ASSISTANT Learn • Practice • Test • Analyze • Improve
A5: A local study desk for Excel 2021. Choose a subject and difficulty, draw a quiz from the question bank, answer in the blue cells, then review the score, explanations, and weak subtopics. History is saved by pasting the green result row into PROGRESS.
A9: START QUIZ | E9: QUIZ RESULTS | I9: STUDY PROGRESS
A10: 1. Choose a topic. 2. Choose difficulty. 3. Choose number of questions. 4. Answer the questions. 5. Check your score. | E10: Last Score | F10: =IF(QUIZ!O6=0,"-",QUIZ!O11) -> 0 / 10 | I10: Total Quizzes | J10: =PROGRESS!B5 -> 6
E11: Accuracy | F11: =IF(QUIZ!O6=0,"-",QUIZ!O12) -> 0 | I11: Average Accuracy | J11: =PROGRESS!F5 -> 0.71666667
E12: Correct Answers | F12: =QUIZ!O8 -> 0 | I12: Best Score | J12: =PROGRESS!H5 -> 1
E13: Weakest Area | F13: =RESULTS!B30 -> Integration | I13: Total Questions Attempted | J13: =PROGRESS!D5 -> 50
A16: HOW TO USE
A17: QUESTION BANK → QUIZ → RESULTS → PROGRESS 1. Add or edit questions on QUESTION_BANK. Only Active = Yes is used. Correct Answer must be A, B, C, or D. 2. On QUIZ, pick Subject, Difficulty, and Questions. Change Shuffle to draw a new set, then clear old answers. 3. Answer in the blue Your Answer cells. Result, score, and accuracy update immediately. 4. Open RESULTS to read explanations, the performance message, and the weakest subtopic. 5. Copy the green history row on RESULTS and Paste Values into the next blank row of tblHistory on PROGRESS. 6. SETTINGS holds the dropdown lists. Open QUESTION BANK or SETTINGS from the links below.
A25: QUESTION BANK | C25: SETTINGS | E25: QUIZ | G25: RESULTS | I25: PROGRESS | K25: AI GENERATOR
A27: WEAK TOPICS

Sheet QUIZ
A1: QUIZ CENTER | AA1: =COUNTIF(QUESTION_BANK!N2:N510,1) -> 14
A2: Select your settings and test your knowledge. | AA2: =IF(OR(NOT(ISNUMBER(K5)),K5<1),0,K5) -> 10
A3: ← HOME | AA3: =MIN(AA1,AA2) -> 10
A5: Subject | B5: Mathematics | F5: Difficulty | G5: Medium | J5: Questions | K5: 10 | N5: CURRENT QUIZ
A6: Shuffle | B6: 1 | C6: Type a new whole number to draw a different quiz. Clear the Your Answer cells before you reshuffle. Questions stay fixed until Shuffle changes. | N6: Total Questions | O6: =AA3 -> 10
A7: =IF(AA1=0,"No matching questions found. Please change your quiz settings or add questions to QUESTION_BANK.",IF(AA1<AA2,"Not enough questions available for this selection. Please choose another topic, difficulty, or question count. Showing "&AA3&" of "&AA2&" requested.","Ready — "&AA3&" questions drawn from "&B5&" / "&G5&". Change Shuffle to draw a new set.")) -> Ready — 10 questions drawn from Mathematics / Medium. Change Shuffle to draw a new set. | N7: Answered | O7: {=SUMPRODUCT(($AA$9:$AA$28<>"")*(I9:I28<>""))} -> 0
A8: Q# | B8: Question | I8: Your Answer | J8: Correct | K8: Result | L8: Explanation | N8: Correct | O8: =COUNTIF(K9:K28,"CORRECT") -> 0
A9: =IF(AA9="","",1) -> 1 | B9: =IF(AA9="","",_xlfn.XLOOKUP(AA9,tblQuestions[Question ID],tblQuestions[Question])&CHAR(10)&"A. "&_xlfn.XLOOKUP(AA9,tblQuestions[Question ID],tblQuestions[Option A])&CHAR(10)&"B. "&_xlfn.XLOOKUP(AA9,tblQuestions[Question ID],tblQuestions[Option B])&CHAR(10)&"C. "&_xlfn.XLOOKUP(AA9,tblQuestions[Question ID],tblQuestions[Option C])&CHAR(10)&"D. "&_xlfn.XLOOKUP(AA9,tblQuestions[Question ID],tblQuestions[Option D])) -> Using substitution, evaluate the indefinite integral of 2x(x^2+1)^3. A. (x^2+1)^4 / 4 + C B. (x^2+1)^3 / 3 + C C. 2(x^2+1)^4 + C D. x^2(x^2+1)^4 + C | J9: =IF(OR(AA9="",I9=""),"",_xlfn.XLOOKUP(AA9,tblQuestions[Question ID],tblQuestions[Correct Answer])) | K9: =IF(AA9="","",IF(I9="","NOT ANSWERED",IF(UPPER(TRIM(I9))=_xlfn.XLOOKUP(AA9,tblQuestions[Question ID],tblQuestions[Correct Answer]),"CORRECT","INCORRECT"))) -> NOT ANSWERED | L9: =IF(OR(AA9="",I9=""),"",_xlfn.XLOOKUP(AA9,tblQuestions[Question ID],tblQuestions[Explanation])) | N9: Incorrect | O9: =COUNTIF(K9:K28,"INCORRECT") -> 0 | AA9: =IF(OR($AA$3<1,1>$AA$3),"",IFERROR(INDEX(QUESTION_BANK!$A$2:$A$510,MATCH(1,QUESTION_BANK!$P$2:$P$510,0)),"")) -> MATH001
A10: =IF(AA10="","",2) -> 2 | B10: =IF(AA10="","",_xlfn.XLOOKUP(AA10,tblQuestions[Question ID],tblQuestions[Question])&CHAR(10)&"A. "&_xlfn.XLOOKUP(AA10,tblQuestions[Question ID],tblQuestions[Option A])&CHAR(10)&"B. "&_xlfn.XLOOKUP(AA10,tblQuestions[Question ID],tblQuestions[Option B])&CHAR(10)&"C. "&_xlfn.XLOOKUP(AA10,tblQuestions[Question ID],tblQuestions[Option C])&CHAR(10)&"D. "&_xlfn.XLOOKUP(AA10,tblQuestions[Question ID],tblQuestions[Option D])) -> What is the derivative of sin(x)? A. -cos(x) B. sin(x) C. cos(x) D. tan(x) | J10: =IF(OR(AA10="",I10=""),"",_xlfn.XLOOKUP(AA10,tblQuestions[Question ID],tblQuestions[Correct Answer])) | K10: =IF(AA10="","",IF(I10="","NOT ANSWERED",IF(UPPER(TRIM(I10))=_xlfn.XLOOKUP(AA10,tblQuestions[Question ID],tblQuestions[Correct Answer]),"CORRECT","INCORRECT"))) -> NOT ANSWERED | L10: =IF(OR(AA10="",I10=""),"",_xlfn.XLOOKUP(AA10,tblQuestions[Question ID],tblQuestions[Explanation])) | N10: Not Answered | O10: =COUNTIF(K9:K28,"NOT ANSWERED") -> 10 | AA10: =IF(OR($AA$3<1,2>$AA$3),"",IFERROR(INDEX(QUESTION_BANK!$A$2:$A$510,MATCH(2,QUESTION_BANK!$P$2:$P$510,0)),"")) -> Q002
A11: =IF(AA11="","",3) -> 3 | B11: =IF(AA11="","",_xlfn.XLOOKUP(AA11,tblQuestions[Question ID],tblQuestions[Question])&CHAR(10)&"A. "&_xlfn.XLOOKUP(AA11,tblQuestions[Question ID],tblQuestions[Option A])&CHAR(10)&"B. "&_xlfn.XLOOKUP(AA11,tblQuestions[Question ID],tblQuestions[Option B])&CHAR(10)&"C. "&_xlfn.XLOOKUP(AA11,tblQuestions[Question ID],tblQuestions[Option C])&CHAR(10)&"D. "&_xlfn.XLOOKUP(AA11,tblQuestions[Question ID],tblQuestions[Option D])) -> Using substitution, evaluate the indefinite integral of 2x e^(x^2). A. e^(x^2) + C B. 2e^(x^2) + C C. x e^(x^2) + C D. e^(2x) + C | J11: =IF(OR(AA11="",I11=""),"",_xlfn.XLOOKUP(AA11,tblQuestions[Question ID],tblQuestions[Correct Answer])) | K11: =IF(AA11="","",IF(I11="","NOT ANSWERED",IF(UPPER(TRIM(I11))=_xlfn.XLOOKUP(AA11,tblQuestions[Question ID],tblQuestions[Correct Answer]),"CORRECT","INCORRECT"))) -> NOT ANSWERED | L11: =IF(OR(AA11="",I11=""),"",_xlfn.XLOOKUP(AA11,tblQuestions[Question ID],tblQuestions[Explanation])) | N11: Score | O11: =IF(O6=0,"—",O8&" / "&O6) -> 0 / 10 | AA11: =IF(OR($AA$3<1,3>$AA$3),"",IFERROR(INDEX(QUESTION_BANK!$A$2:$A$510,MATCH(3,QUESTION_BANK!$P$2:$P$510,0)),"")) -> MATH002
A12: =IF(AA12="","",4) -> 4 | B12: =IF(AA12="","",_xlfn.XLOOKUP(AA12,tblQuestions[Question ID],tblQuestions[Question])&CHAR(10)&"A. "&_xlfn.XLOOKUP(AA12,tblQuestions[Question ID],tblQuestions[Option A])&CHAR(10)&"B. "&_xlfn.XLOOKUP(AA12,tblQuestions[Question ID],tblQuestions[Option B])&CHAR(10)&"C. "&_xlfn.XLOOKUP(AA12,tblQuestions[Question ID],tblQuestions[Option C])&CHAR(10)&"D. "&_xlfn.XLOOKUP(AA12,tblQuestions[Question ID],tblQuestions[Option D])) -> Evaluate the definite integral of 2x from 0 to 1. A. 1 B. 2 C. 0 D. 1/2 | J12: =IF(OR(AA12="",I12=""),"",_xlfn.XLOOKUP(AA12,tblQuestions[Question ID],tblQuestions[Correct Answer])) | K12: =IF(AA12="","",IF(I12="","NOT ANSWERED",IF(UPPER(TRIM(I12))=_xlfn.XLOOKUP(AA12,tblQuestions[Question ID],tblQuestions[Correct Answer]),"CORRECT","INCORRECT"))) -> NOT ANSWERED | L12: =IF(OR(AA12="",I12=""),"",_xlfn.XLOOKUP(AA12,tblQuestions[Question ID],tblQuestions[Explanation])) | N12: Accuracy | O12: =IF(O6=0,"—",O8/O6) -> 0 | AA12: =IF(OR($AA$3<1,4>$AA$3),"",IFERROR(INDEX(QUESTION_BANK!$A$2:$A$510,MATCH(4,QUESTION_BANK!$P$2:$P$510,0)),"")) -> MATH003
A13: =IF(AA13="","",5) -> 5 | B13: =IF(AA13="","",_xlfn.XLOOKUP(AA13,tblQuestions[Question ID],tblQuestions[Question])&CHAR(10)&"A. "&_xlfn.XLOOKUP(AA13,tblQuestions[Question ID],tblQuestions[Option A])&CHAR(10)&"B. "&_xlfn.XLOOKUP(AA13,tblQuestions[Question ID],tblQuestions[Option B])&CHAR(10)&"C. "&_xlfn.XLOOKUP(AA13,tblQuestions[Question ID],tblQuestions[Option C])&CHAR(10)&"D. "&_xlfn.XLOOKUP(AA13,tblQuestions[Question ID],tblQuestions[Option D])) -> What is the indefinite integral of 1/x? A. x + C B. 1/x² + C C. ln|x| + C D. e^x + C | J13: =IF(OR(AA13="",I13=""),"",_xlfn.XLOOKUP(AA13,tblQuestions[Question ID],tblQuestions[Correct Answer])) | K13: =IF(AA13="","",IF(I13="","NOT ANSWERED",IF(UPPER(TRIM(I13))=_xlfn.XLOOKUP(AA13,tblQuestions[Question ID],tblQuestions[Correct Answer]),"CORRECT","INCORRECT"))) -> NOT ANSWERED | L13: =IF(OR(AA13="",I13=""),"",_xlfn.XLOOKUP(AA13,tblQuestions[Question ID],tblQuestions[Explanation])) | AA13: =IF(OR($AA$3<1,5>$AA$3),"",IFERROR(INDEX(QUESTION_BANK!$A$2:$A$510,MATCH(5,QUESTION_BANK!$P$2:$P$510,0)),"")) -> Q004
A14: =IF(AA14="","",6) -> 6 | B14: =IF(AA14="","",_xlfn.XLOOKUP(AA14,tblQuestions[Question ID],tblQuestions[Question])&CHAR(10)&"A. "&_xlfn.XLOOKUP(AA14,tblQuestions[Question ID],tblQuestions[Option A])&CHAR(10)&"B. "&_xlfn.XLOOKUP(AA14,tblQuestions[Question ID],tblQuestions[Option B])&CHAR(10)&"C. "&_xlfn.XLOOKUP(AA14,tblQuestions[Question ID],tblQuestions[Option C])&CHAR(10)&"D. "&_xlfn.XLOOKUP(AA14,tblQuestions[Question ID],tblQuestions[Option D])) -> Evaluate the definite integral of 3x^2 from 0 to 2. A. 8 B. 12 C. 4 D. 6 | J14: =IF(OR(AA14="",I14=""),"",_xlfn.XLOOKUP(AA14,tblQuestions[Question ID],tblQuestions[Correct Answer])) | K14: =IF(AA14="","",IF(I14="","NOT ANSWERED",IF(UPPER(TRIM(I14))=_xlfn.XLOOKUP(AA14,tblQuestions[Question ID],tblQuestions[Correct Answer]),"CORRECT","INCORRECT"))) -> NOT ANSWERED | L14: =IF(OR(AA14="",I14=""),"",_xlfn.XLOOKUP(AA14,tblQuestions[Question ID],tblQuestions[Explanation])) | N14: → RESULTS | AA14: =IF(OR($AA$3<1,6>$AA$3),"",IFERROR(INDEX(QUESTION_BANK!$A$2:$A$510,MATCH(6,QUESTION_BANK!$P$2:$P$510,0)),"")) -> MATH004
A15: =IF(AA15="","",7) -> 7 | B15: =IF(AA15="","",_xlfn.XLOOKUP(AA15,tblQuestions[Question ID],tblQuestions[Question])&CHAR(10)&"A. "&_xlfn.XLOOKUP(AA15,tblQuestions[Question ID],tblQuestions[Option A])&CHAR(10)&"B. "&_xlfn.XLOOKUP(AA15,tblQuestions[Question ID],tblQuestions[Option B])&CHAR(10)&"C. "&_xlfn.XLOOKUP(AA15,tblQuestions[Question ID],tblQuestions[Option C])&CHAR(10)&"D. "&_xlfn.XLOOKUP(AA15,tblQuestions[Question ID],tblQuestions[Option D])) -> Using substitution, evaluate the indefinite integral of 2x/(x^2+1). A. ln|x^2+1| + C B. 2 ln|x^2+1| + C C. ln|2x| + C D. arctan(x^2) + C | J15: =IF(OR(AA15="",I15=""),"",_xlfn.XLOOKUP(AA15,tblQuestions[Question ID],tblQuestions[Correct Answer])) | K15: =IF(AA15="","",IF(I15="","NOT ANSWERED",IF(UPPER(TRIM(I15))=_xlfn.XLOOKUP(AA15,tblQuestions[Question ID],tblQuestions[Correct Answer]),"CORRECT","INCORRECT"))) -> NOT ANSWERED | L15: =IF(OR(AA15="",I15=""),"",_xlfn.XLOOKUP(AA15,tblQuestions[Question ID],tblQuestions[Explanation])) | AA15: =IF(OR($AA$3<1,7>$AA$3),"",IFERROR(INDEX(QUESTION_BANK!$A$2:$A$510,MATCH(7,QUESTION_BANK!$P$2:$P$510,0)),"")) -> MATH005
A16: =IF(AA16="","",8) -> 8 | B16: =IF(AA16="","",_xlfn.XLOOKUP(AA16,tblQuestions[Question ID],tblQuestions[Question])&CHAR(10)&"A. "&_xlfn.XLOOKUP(AA16,tblQuestions[Question ID],tblQuestions[Option A])&CHAR(10)&"B. "&_xlfn.XLOOKUP(AA16,tblQuestions[Question ID],tblQuestions[Option B])&CHAR(10)&"C. "&_xlfn.XLOOKUP(AA16,tblQuestions[Question ID],tblQuestions[Option C])&CHAR(10)&"D. "&_xlfn.XLOOKUP(AA16,tblQuestions[Question ID],tblQuestions[Option D])) -> What are the roots of x² − 5x + 6 = 0? A. 1 and 6 B. 2 and 3 C. −2 and −3 D. 5 and 6 | J16: =IF(OR(AA16="",I16=""),"",_xlfn.XLOOKUP(AA16,tblQuestions[Question ID],tblQuestions[Correct Answer])) | K16: =IF(AA16="","",IF(I16="","NOT ANSWERED",IF(UPPER(TRIM(I16))=_xlfn.XLOOKUP(AA16,tblQuestions[Question ID],tblQuestions[Correct Answer]),"CORRECT","INCORRECT"))) -> NOT ANSWERED | L16: =IF(OR(AA16="",I16=""),"",_xlfn.XLOOKUP(AA16,tblQuestions[Question ID],tblQuestions[Explanation])) | AA16: =IF(OR($AA$3<1,8>$AA$3),"",IFERROR(INDEX(QUESTION_BANK!$A$2:$A$510,MATCH(8,QUESTION_BANK!$P$2:$P$510,0)),"")) -> Q006
A17: =IF(AA17="","",9) -> 9 | B17: =IF(AA17="","",_xlfn.XLOOKUP(AA17,tblQuestions[Question ID],tblQuestions[Question])&CHAR(10)&"A. "&_xlfn.XLOOKUP(AA17,tblQuestions[Question ID],tblQuestions[Option A])&CHAR(10)&"B. "&_xlfn.XLOOKUP(AA17,tblQuestions[Question ID],tblQuestions[Option B])&CHAR(10)&"C. "&_xlfn.XLOOKUP(AA17,tblQuestions[Question ID],tblQuestions[Option C])&CHAR(10)&"D. "&_xlfn.XLOOKUP(AA17,tblQuestions[Question ID],tblQuestions[Option D])) -> Evaluate the definite integral of 1/x from 1 to e. A. 1 B. e C. 0 D. e-1 | J17: =IF(OR(AA17="",I17=""),"",_xlfn.XLOOKUP(AA17,tblQuestions[Question ID],tblQuestions[Correct Answer])) | K17: =IF(AA17="","",IF(I17="","NOT ANSWERED",IF(UPPER(TRIM(I17))=_xlfn.XLOOKUP(AA17,tblQuestions[Question ID],tblQuestions[Correct Answer]),"CORRECT","INCORRECT"))) -> NOT ANSWERED | L17: =IF(OR(AA17="",I17=""),"",_xlfn.XLOOKUP(AA17,tblQuestions[Question ID],tblQuestions[Explanation])) | AA17: =IF(OR($AA$3<1,9>$AA$3),"",IFERROR(INDEX(QUESTION_BANK!$A$2:$A$510,MATCH(9,QUESTION_BANK!$P$2:$P$510,0)),"")) -> MATH006
A18: =IF(AA18="","",10) -> 10 | B18: =IF(AA18="","",_xlfn.XLOOKUP(AA18,tblQuestions[Question ID],tblQuestions[Question])&CHAR(10)&"A. "&_xlfn.XLOOKUP(AA18,tblQuestions[Question ID],tblQuestions[Option A])&CHAR(10)&"B. "&_xlfn.XLOOKUP(AA18,tblQuestions[Question ID],tblQuestions[Option B])&CHAR(10)&"C. "&_xlfn.XLOOKUP(AA18,tblQuestions[Question ID],tblQuestions[Option C])&CHAR(10)&"D. "&_xlfn.XLOOKUP(AA18,tblQuestions[Question ID],tblQuestions[Option D])) -> Using the substitution u = sin(x), evaluate the indefinite integral of sin(x)cos(x). A. (1/2) sin^2(x) + C B. sin^2(x) + C C. cos^2(x) + C D. negative cos(x) + C | J18: =IF(OR(AA18="",I18=""),"",_xlfn.XLOOKUP(AA18,tblQuestions[Question ID],tblQuestions[Correct Answer])) | K18: =IF(AA18="","",IF(I18="","NOT ANSWERED",IF(UPPER(TRIM(I18))=_xlfn.XLOOKUP(AA18,tblQuestions[Question ID],tblQuestions[Correct Answer]),"CORRECT","INCORRECT"))) -> NOT ANSWERED | L18: =IF(OR(AA18="",I18=""),"",_xlfn.XLOOKUP(AA18,tblQuestions[Question ID],tblQuestions[Explanation])) | AA18: =IF(OR($AA$3<1,10>$AA$3),"",IFERROR(INDEX(QUESTION_BANK!$A$2:$A$510,MATCH(10,QUESTION_BANK!$P$2:$P$510,0)),"")) -> MATH007
A19: =IF(AA19="","",11) | B19: =IF(AA19="","",_xlfn.XLOOKUP(AA19,tblQuestions[Question ID],tblQuestions[Question])&CHAR(10)&"A. "&_xlfn.XLOOKUP(AA19,tblQuestions[Question ID],tblQuestions[Option A])&CHAR(10)&"B. "&_xlfn.XLOOKUP(AA19,tblQuestions[Question ID],tblQuestions[Option B])&CHAR(10)&"C. "&_xlfn.XLOOKUP(AA19,tblQuestions[Question ID],tblQuestions[Option C])&CHAR(10)&"D. "&_xlfn.XLOOKUP(AA19,tblQuestions[Question ID],tblQuestions[Option D])) | J19: =IF(OR(AA19="",I19=""),"",_xlfn.XLOOKUP(AA19,tblQuestions[Question ID],tblQuestions[Correct Answer])) | K19: =IF(AA19="","",IF(I19="","NOT ANSWERED",IF(UPPER(TRIM(I19))=_xlfn.XLOOKUP(AA19,tblQuestions[Question ID],tblQuestions[Correct Answer]),"CORRECT","INCORRECT"))) | L19: =IF(OR(AA19="",I19=""),"",_xlfn.XLOOKUP(AA19,tblQuestions[Question ID],tblQuestions[Explanation])) | AA19: =IF(OR($AA$3<1,11>$AA$3),"",IFERROR(INDEX(QUESTION_BANK!$A$2:$A$510,MATCH(11,QUESTION_BANK!$P$2:$P$510,0)),""))
A20: =IF(AA20="","",12) | B20: =IF(AA20="","",_xlfn.XLOOKUP(AA20,tblQuestions[Question ID],tblQuestions[Question])&CHAR(10)&"A. "&_xlfn.XLOOKUP(AA20,tblQuestions[Question ID],tblQuestions[Option A])&CHAR(10)&"B. "&_xlfn.XLOOKUP(AA20,tblQuestions[Question ID],tblQuestions[Option B])&CHAR(10)&"C. "&_xlfn.XLOOKUP(AA20,tblQuestions[Question ID],tblQuestions[Option C])&CHAR(10)&"D. "&_xlfn.XLOOKUP(AA20,tblQuestions[Question ID],tblQuestions[Option D])) | J20: =IF(OR(AA20="",I20=""),"",_xlfn.XLOOKUP(AA20,tblQuestions[Question ID],tblQuestions[Correct Answer])) | K20: =IF(AA20="","",IF(I20="","NOT ANSWERED",IF(UPPER(TRIM(I20))=_xlfn.XLOOKUP(AA20,tblQuestions[Question ID],tblQuestions[Correct Answer]),"CORRECT","INCORRECT"))) | L20: =IF(OR(AA20="",I20=""),"",_xlfn.XLOOKUP(AA20,tblQuestions[Question ID],tblQuestions[Explanation])) | AA20: =IF(OR($AA$3<1,12>$AA$3),"",IFERROR(INDEX(QUESTION_BANK!$A$2:$A$510,MATCH(12,QUESTION_BANK!$P$2:$P$510,0)),""))
A21: =IF(AA21="","",13) | B21: =IF(AA21="","",_xlfn.XLOOKUP(AA21,tblQuestions[Question ID],tblQuestions[Question])&CHAR(10)&"A. "&_xlfn.XLOOKUP(AA21,tblQuestions[Question ID],tblQuestions[Option A])&CHAR(10)&"B. "&_xlfn.XLOOKUP(AA21,tblQuestions[Question ID],tblQuestions[Option B])&CHAR(10)&"C. "&_xlfn.XLOOKUP(AA21,tblQuestions[Question ID],tblQuestions[Option C])&CHAR(10)&"D. "&_xlfn.XLOOKUP(AA21,tblQuestions[Question ID],tblQuestions[Option D])) | J21: =IF(OR(AA21="",I21=""),"",_xlfn.XLOOKUP(AA21,tblQuestions[Question ID],tblQuestions[Correct Answer])) | K21: =IF(AA21="","",IF(I21="","NOT ANSWERED",IF(UPPER(TRIM(I21))=_xlfn.XLOOKUP(AA21,tblQuestions[Question ID],tblQuestions[Correct Answer]),"CORRECT","INCORRECT"))) | L21: =IF(OR(AA21="",I21=""),"",_xlfn.XLOOKUP(AA21,tblQuestions[Question ID],tblQuestions[Explanation])) | AA21: =IF(OR($AA$3<1,13>$AA$3),"",IFERROR(INDEX(QUESTION_BANK!$A$2:$A$510,MATCH(13,QUESTION_BANK!$P$2:$P$510,0)),""))
A22: =IF(AA22="","",14) | B22: =IF(AA22="","",_xlfn.XLOOKUP(AA22,tblQuestions[Question ID],tblQuestions[Question])&CHAR(10)&"A. "&_xlfn.XLOOKUP(AA22,tblQuestions[Question ID],tblQuestions[Option A])&CHAR(10)&"B. "&_xlfn.XLOOKUP(AA22,tblQuestions[Question ID],tblQuestions[Option B])&CHAR(10)&"C. "&_xlfn.XLOOKUP(AA22,tblQuestions[Question ID],tblQuestions[Option C])&CHAR(10)&"D. "&_xlfn.XLOOKUP(AA22,tblQuestions[Question ID],tblQuestions[Option D])) | J22: =IF(OR(AA22="",I22=""),"",_xlfn.XLOOKUP(AA22,tblQuestions[Question ID],tblQuestions[Correct Answer])) | K22: =IF(AA22="","",IF(I22="","NOT ANSWERED",IF(UPPER(TRIM(I22))=_xlfn.XLOOKUP(AA22,tblQuestions[Question ID],tblQuestions[Correct Answer]),"CORRECT","INCORRECT"))) | L22: =IF(OR(AA22="",I22=""),"",_xlfn.XLOOKUP(AA22,tblQuestions[Question ID],tblQuestions[Explanation])) | AA22: =IF(OR($AA$3<1,14>$AA$3),"",IFERROR(INDEX(QUESTION_BANK!$A$2:$A$510,MATCH(14,QUESTION_BANK!$P$2:$P$510,0)),""))
A23: =IF(AA23="","",15) | B23: =IF(AA23="","",_xlfn.XLOOKUP(AA23,tblQuestions[Question ID],tblQuestions[Question])&CHAR(10)&"A. "&_xlfn.XLOOKUP(AA23,tblQuestions[Question ID],tblQuestions[Option A])&CHAR(10)&"B. "&_xlfn.XLOOKUP(AA23,tblQuestions[Question ID],tblQuestions[Option B])&CHAR(10)&"C. "&_xlfn.XLOOKUP(AA23,tblQuestions[Question ID],tblQuestions[Option C])&CHAR(10)&"D. "&_xlfn.XLOOKUP(AA23,tblQuestions[Question ID],tblQuestions[Option D])) | J23: =IF(OR(AA23="",I23=""),"",_xlfn.XLOOKUP(AA23,tblQuestions[Question ID],tblQuestions[Correct Answer])) | K23: =IF(AA23="","",IF(I23="","NOT ANSWERED",IF(UPPER(TRIM(I23))=_xlfn.XLOOKUP(AA23,tblQuestions[Question ID],tblQuestions[Correct Answer]),"CORRECT","INCORRECT"))) | L23: =IF(OR(AA23="",I23=""),"",_xlfn.XLOOKUP(AA23,tblQuestions[Question ID],tblQuestions[Explanation])) | AA23: =IF(OR($AA$3<1,15>$AA$3),"",IFERROR(INDEX(QUESTION_BANK!$A$2:$A$510,MATCH(15,QUESTION_BANK!$P$2:$P$510,0)),""))
A24: =IF(AA24="","",16) | B24: =IF(AA24="","",_xlfn.XLOOKUP(AA24,tblQuestions[Question ID],tblQuestions[Question])&CHAR(10)&"A. "&_xlfn.XLOOKUP(AA24,tblQuestions[Question ID],tblQuestions[Option A])&CHAR(10)&"B. "&_xlfn.XLOOKUP(AA24,tblQuestions[Question ID],tblQuestions[Option B])&CHAR(10)&"C. "&_xlfn.XLOOKUP(AA24,tblQuestions[Question ID],tblQuestions[Option C])&CHAR(10)&"D. "&_xlfn.XLOOKUP(AA24,tblQuestions[Question ID],tblQuestions[Option D])) | J24: =IF(OR(AA24="",I24=""),"",_xlfn.XLOOKUP(AA24,tblQuestions[Question ID],tblQuestions[Correct Answer])) | K24: =IF(AA24="","",IF(I24="","NOT ANSWERED",IF(UPPER(TRIM(I24))=_xlfn.XLOOKUP(AA24,tblQuestions[Question ID],tblQuestions[Correct Answer]),"CORRECT","INCORRECT"))) | L24: =IF(OR(AA24="",I24=""),"",_xlfn.XLOOKUP(AA24,tblQuestions[Question ID],tblQuestions[Explanation])) | AA24: =IF(OR($AA$3<1,16>$AA$3),"",IFERROR(INDEX(QUESTION_BANK!$A$2:$A$510,MATCH(16,QUESTION_BANK!$P$2:$P$510,0)),""))
A25: =IF(AA25="","",17) | B25: =IF(AA25="","",_xlfn.XLOOKUP(AA25,tblQuestions[Question ID],tblQuestions[Question])&CHAR(10)&"A. "&_xlfn.XLOOKUP(AA25,tblQuestions[Question ID],tblQuestions[Option A])&CHAR(10)&"B. "&_xlfn.XLOOKUP(AA25,tblQuestions[Question ID],tblQuestions[Option B])&CHAR(10)&"C. "&_xlfn.XLOOKUP(AA25,tblQuestions[Question ID],tblQuestions[Option C])&CHAR(10)&"D. "&_xlfn.XLOOKUP(AA25,tblQuestions[Question ID],tblQuestions[Option D])) | J25: =IF(OR(AA25="",I25=""),"",_xlfn.XLOOKUP(AA25,tblQuestions[Question ID],tblQuestions[Correct Answer])) | K25: =IF(AA25="","",IF(I25="","NOT ANSWERED",IF(UPPER(TRIM(I25))=_xlfn.XLOOKUP(AA25,tblQuestions[Question ID],tblQuestions[Correct Answer]),"CORRECT","INCORRECT"))) | L25: =IF(OR(AA25="",I25=""),"",_xlfn.XLOOKUP(AA25,tblQuestions[Question ID],tblQuestions[Explanation])) | AA25: =IF(OR($AA$3<1,17>$AA$3),"",IFERROR(INDEX(QUESTION_BANK!$A$2:$A$510,MATCH(17,QUESTION_BANK!$P$2:$P$510,0)),""))
A26: =IF(AA26="","",18) | B26: =IF(AA26="","",_xlfn.XLOOKUP(AA26,tblQuestions[Question ID],tblQuestions[Question])&CHAR(10)&"A. "&_xlfn.XLOOKUP(AA26,tblQuestions[Question ID],tblQuestions[Option A])&CHAR(10)&"B. "&_xlfn.XLOOKUP(AA26,tblQuestions[Question ID],tblQuestions[Option B])&CHAR(10)&"C. "&_xlfn.XLOOKUP(AA26,tblQuestions[Question ID],tblQuestions[Option C])&CHAR(10)&"D. "&_xlfn.XLOOKUP(AA26,tblQuestions[Question ID],tblQuestions[Option D])) | J26: =IF(OR(AA26="",I26=""),"",_xlfn.XLOOKUP(AA26,tblQuestions[Question ID],tblQuestions[Correct Answer])) | K26: =IF(AA26="","",IF(I26="","NOT ANSWERED",IF(UPPER(TRIM(I26))=_xlfn.XLOOKUP(AA26,tblQuestions[Question ID],tblQuestions[Correct Answer]),"CORRECT","INCORRECT"))) | L26: =IF(OR(AA26="",I26=""),"",_xlfn.XLOOKUP(AA26,tblQuestions[Question ID],tblQuestions[Explanation])) | AA26: =IF(OR($AA$3<1,18>$AA$3),"",IFERROR(INDEX(QUESTION_BANK!$A$2:$A$510,MATCH(18,QUESTION_BANK!$P$2:$P$510,0)),""))
A27: =IF(AA27="","",19) | B27: =IF(AA27="","",_xlfn.XLOOKUP(AA27,tblQuestions[Question ID],tblQuestions[Question])&CHAR(10)&"A. "&_xlfn.XLOOKUP(AA27,tblQuestions[Question ID],tblQuestions[Option A])&CHAR(10)&"B. "&_xlfn.XLOOKUP(AA27,tblQuestions[Question ID],tblQuestions[Option B])&CHAR(10)&"C. "&_xlfn.XLOOKUP(AA27,tblQuestions[Question ID],tblQuestions[Option C])&CHAR(10)&"D. "&_xlfn.XLOOKUP(AA27,tblQuestions[Question ID],tblQuestions[Option D])) | J27: =IF(OR(AA27="",I27=""),"",_xlfn.XLOOKUP(AA27,tblQuestions[Question ID],tblQuestions[Correct Answer])) | K27: =IF(AA27="","",IF(I27="","NOT ANSWERED",IF(UPPER(TRIM(I27))=_xlfn.XLOOKUP(AA27,tblQuestions[Question ID],tblQuestions[Correct Answer]),"CORRECT","INCORRECT"))) | L27: =IF(OR(AA27="",I27=""),"",_xlfn.XLOOKUP(AA27,tblQuestions[Question ID],tblQuestions[Explanation])) | AA27: =IF(OR($AA$3<1,19>$AA$3),"",IFERROR(INDEX(QUESTION_BANK!$A$2:$A$510,MATCH(19,QUESTION_BANK!$P$2:$P$510,0)),""))
A28: =IF(AA28="","",20) | B28: =IF(AA28="","",_xlfn.XLOOKUP(AA28,tblQuestions[Question ID],tblQuestions[Question])&CHAR(10)&"A. "&_xlfn.XLOOKUP(AA28,tblQuestions[Question ID],tblQuestions[Option A])&CHAR(10)&"B. "&_xlfn.XLOOKUP(AA28,tblQuestions[Question ID],tblQuestions[Option B])&CHAR(10)&"C. "&_xlfn.XLOOKUP(AA28,tblQuestions[Question ID],tblQuestions[Option C])&CHAR(10)&"D. "&_xlfn.XLOOKUP(AA28,tblQuestions[Question ID],tblQuestions[Option D])) | J28: =IF(OR(AA28="",I28=""),"",_xlfn.XLOOKUP(AA28,tblQuestions[Question ID],tblQuestions[Correct Answer])) | K28: =IF(AA28="","",IF(I28="","NOT ANSWERED",IF(UPPER(TRIM(I28))=_xlfn.XLOOKUP(AA28,tblQuestions[Question ID],tblQuestions[Correct Answer]),"CORRECT","INCORRECT"))) | L28: =IF(OR(AA28="",I28=""),"",_xlfn.XLOOKUP(AA28,tblQuestions[Question ID],tblQuestions[Explanation])) | AA28: =IF(OR($AA$3<1,20>$AA$3),"",IFERROR(INDEX(QUESTION_BANK!$A$2:$A$510,MATCH(20,QUESTION_BANK!$P$2:$P$510,0)),""))

Sheet QUESTION_BANK
A1: Question ID | B1: Subject | C1: Topic | D1: Subtopic | E1: Difficulty | F1: Question | G1: Option A | H1: Option B | I1: Option C | J1: Option D | K1: Correct Answer | L1: Explanation | M1: Active | N1: Eligible | O1: Rank Key | P1: Draw Rank | R1: AI QUESTION GENERATOR
A2: Q001 | B2: Mathematics | C2: Calculus | D2: Derivatives | E2: Easy | F2: What is the derivative of x²? | G2: x | H2: 2x | I2: x² | J2: 2 | K2: B | L2: The power rule gives d/dx(x²) = 2x. | M2: Yes | N2: =IF(AND(M2="Yes",OR(QUIZ!$B$5="All Subjects",B2=QUIZ!$B$5),OR(QUIZ!$G$5="All Difficulties",E2=QUIZ!$G$5)),1,0) -> 0 | O2: =IF(N2=0,999999,MOD(IFERROR(VALUE(RIGHT(A2,3)),ROW())*7919+IF(N(QUIZ!$B$6)=0,1,QUIZ!$B$6)*104729+ROW()*IF(N(QUIZ!$B$6)=0,1,QUIZ!$B$6),999983)+ROW()/1000) -> 999999 | P2: =IF(N2=0,"",COUNTIFS($N$2:$N$510,1,$O$2:$O$510,"<"&O2)+1)
A3: Q002 | B3: Mathematics | C3: Calculus | D3: Derivatives | E3: Medium | F3: What is the derivative of sin(x)? | G3: -cos(x) | H3: sin(x) | I3: cos(x) | J3: tan(x) | K3: C | L3: The derivative of sin(x) is cos(x). | M3: Yes | N3: =IF(AND(M3="Yes",OR(QUIZ!$B$5="All Subjects",B3=QUIZ!$B$5),OR(QUIZ!$G$5="All Difficulties",E3=QUIZ!$G$5)),1,0) -> 1 | O3: =IF(N3=0,999999,MOD(IFERROR(VALUE(RIGHT(A3,3)),ROW())*7919+IF(N(QUIZ!$B$6)=0,1,QUIZ!$B$6)*104729+ROW()*IF(N(QUIZ!$B$6)=0,1,QUIZ!$B$6),999983)+ROW()/1000) -> 120570 | P3: =IF(N3=0,"",COUNTIFS($N$2:$N$510,1,$O$2:$O$510,"<"&O3)+1) -> 2
A4: Q003 | B4: Mathematics | C4: Calculus | D4: Integration | E4: Easy | F4: What is the indefinite integral of 2x? | G4: x² + C | H4: 2x² + C | I4: x + C | J4: 2 + C | K4: A | L4: Integrating 2x with the power rule gives x² + C. | M4: Yes | N4: =IF(AND(M4="Yes",OR(QUIZ!$B$5="All Subjects",B4=QUIZ!$B$5),OR(QUIZ!$G$5="All Difficulties",E4=QUIZ!$G$5)),1,0) -> 0 | O4: =IF(N4=0,999999,MOD(IFERROR(VALUE(RIGHT(A4,3)),ROW())*7919+IF(N(QUIZ!$B$6)=0,1,QUIZ!$B$6)*104729+ROW()*IF(N(QUIZ!$B$6)=0,1,QUIZ!$B$6),999983)+ROW()/1000) -> 999999 | P4: =IF(N4=0,"",COUNTIFS($N$2:$N$510,1,$O$2:$O$510,"<"&O4)+1)
A5: Q004 | B5: Mathematics | C5: Calculus | D5: Integration | E5: Medium | F5: What is the indefinite integral of 1/x? | G5: x + C | H5: 1/x² + C | I5: ln|x| + C | J5: e^x + C | K5: C | L5: The integral of 1/x is the natural log of the absolute value of x, plus C. | M5: Yes | N5: =IF(AND(M5="Yes",OR(QUIZ!$B$5="All Subjects",B5=QUIZ!$B$5),OR(QUIZ!$G$5="All Difficulties",E5=QUIZ!$G$5)),1,0) -> 1 | O5: =IF(N5=0,999999,MOD(IFERROR(VALUE(RIGHT(A5,3)),ROW())*7919+IF(N(QUIZ!$B$6)=0,1,QUIZ!$B$6)*104729+ROW()*IF(N(QUIZ!$B$6)=0,1,QUIZ!$B$6),999983)+ROW()/1000) -> 136410.01 | P5: =IF(N5=0,"",COUNTIFS($N$2:$N$510,1,$O$2:$O$510,"<"&O5)+1) -> 5
A6: Q005 | B6: Mathematics | C6: Algebra | D6: Linear Equations | E6: Easy | F6: Solve 2x + 3 = 11. | G6: x = 3 | H6: x = 4 | I6: x = 5 | J6: x = 7 | K6: B | L6: Subtract 3 from both sides, then divide by 2: x = 4. | M6: Yes | N6: =IF(AND(M6="Yes",OR(QUIZ!$B$5="All Subjects",B6=QUIZ!$B$5),OR(QUIZ!$G$5="All Difficulties",E6=QUIZ!$G$5)),1,0) -> 0 | O6: =IF(N6=0,999999,MOD(IFERROR(VALUE(RIGHT(A6,3)),ROW())*7919+IF(N(QUIZ!$B$6)=0,1,QUIZ!$B$6)*104729+ROW()*IF(N(QUIZ!$B$6)=0,1,QUIZ!$B$6),999983)+ROW()/1000) -> 999999 | P6: =IF(N6=0,"",COUNTIFS($N$2:$N$510,1,$O$2:$O$510,"<"&O6)+1)
A7: Q006 | B7: Mathematics | C7: Algebra | D7: Quadratic Equations | E7: Medium | F7: What are the roots of x² − 5x + 6 = 0? | G7: 1 and 6 | H7: 2 and 3 | I7: −2 and −3 | J7: 5 and 6 | K7: B | L7: The quadratic factors as (x − 2)(x − 3) = 0. | M7: Yes | N7: =IF(AND(M7="Yes",OR(QUIZ!$B$5="All Subjects",B7=QUIZ!$B$5),OR(QUIZ!$G$5="All Difficulties",E7=QUIZ!$G$5)),1,0) -> 1 | O7: =IF(N7=0,999999,MOD(IFERROR(VALUE(RIGHT(A7,3)),ROW())*7919+IF(N(QUIZ!$B$6)=0,1,QUIZ!$B$6)*104729+ROW()*IF(N(QUIZ!$B$6)=0,1,QUIZ!$B$6),999983)+ROW()/1000) -> 152250.01 | P7: =IF(N7=0,"",COUNTIFS($N$2:$N$510,1,$O$2:$O$510,"<"&O7)+1) -> 8
A8: Q007 | B8: Mathematics | C8: Statistics | D8: Descriptive | E8: Easy | F8: What is the mean of 2, 4, 6, and 8? | G8: 4 | H8: 5 | I8: 6 | J8: 8 | K8: B | L8: The mean is (2 + 4 + 6 + 8) / 4 = 5. | M8: Yes | N8: =IF(AND(M8="Yes",OR(QUIZ!$B$5="All Subjects",B8=QUIZ!$B$5),OR(QUIZ!$G$5="All Difficulties",E8=QUIZ!$G$5)),1,0) -> 0 | O8: =IF(N8=0,999999,MOD(IFERROR(VALUE(RIGHT(A8,3)),ROW())*7919+IF(N(QUIZ!$B$6)=0,1,QUIZ!$B$6)*104729+ROW()*IF(N(QUIZ!$B$6)=0,1,QUIZ!$B$6),999983)+ROW()/1000) -> 999999 | P8: =IF(N8=0,"",COUNTIFS($N$2:$N$510,1,$O$2:$O$510,"<"&O8)+1)
A9: Q008 | B9: Mathematics | C9: Statistics | D9: Probability | E9: Medium | F9: A fair coin is flipped twice. What is the probability of two heads? | G9: 1/2 | H9: 1/3 | I9: 1/4 | J9: 1/8 | K9: C | L9: The flips are independent, so (1/2) × (1/2) = 1/4. | M9: Yes | N9: =IF(AND(M9="Yes",OR(QUIZ!$B$5="All Subjects",B9=QUIZ!$B$5),OR(QUIZ!$G$5="All Difficulties",E9=QUIZ!$G$5)),1,0) -> 1 | O9: =IF(N9=0,999999,MOD(IFERROR(VALUE(RIGHT(A9,3)),ROW())*7919+IF(N(QUIZ!$B$6)=0,1,QUIZ!$B$6)*104729+ROW()*IF(N(QUIZ!$B$6)=0,1,QUIZ!$B$6),999983)+ROW()/1000) -> 168090.01 | P9: =IF(N9=0,"",COUNTIFS($N$2:$N$510,1,$O$2:$O$510,"<"&O9)+1) -> 11
A10: Q009 | B10: Accounting | C10: Journal Entries | D10: Debits and Credits | E10: Easy | F10: Which account normally increases with a debit? | G10: Revenue | H10: Liability | I10: Asset | J10: Owner's equity | K10: C | L10: Assets and expenses increase with debits. Revenue, liabilities, and equity increase with credits. | M10: Yes | N10: =IF(AND(M10="Yes",OR(QUIZ!$B$5="All Subjects",B10=QUIZ!$B$5),OR(QUIZ!$G$5="All Difficulties",E10=QUIZ!$G$5)),1,0) -> 0 | O10: =IF(N10=0,999999,MOD(IFERROR(VALUE(RIGHT(A10,3)),ROW())*7919+IF(N(QUIZ!$B$6)=0,1,QUIZ!$B$6)*104729+ROW()*IF(N(QUIZ!$B$6)=0,1,QUIZ!$B$6),999983)+ROW()/1000) -> 999999 | P10: =IF(N10=0,"",COUNTIFS($N$2:$N$510,1,$O$2:$O$510,"<"&O10)+1)
A11: Q010 | B11: Accounting | C11: Journal Entries | D11: Adjusting Entries | E11: Medium | F11: The adjusting entry for equipment depreciation includes a debit to: | G11: Equipment | H11: Accumulated depreciation | I11: Depreciation expense | J11: Cash | K11: C | L11: Debit depreciation expense and credit accumulated depreciation. | M11: Yes | N11: =IF(AND(M11="Yes",OR(QUIZ!$B$5="All Subjects",B11=QUIZ!$B$5),OR(QUIZ!$G$5="All Difficulties",E11=QUIZ!$G$5)),1,0) -> 0 | O11: =IF(N11=0,999999,MOD(IFERROR(VALUE(RIGHT(A11,3)),ROW())*7919+IF(N(QUIZ!$B$6)=0,1,QUIZ!$B$6)*104729+ROW()*IF(N(QUIZ!$B$6)=0,1,QUIZ!$B$6),999983)+ROW()/1000) -> 999999 | P11: =IF(N11=0,"",COUNTIFS($N$2:$N$510,1,$O$2:$O$510,"<"&O11)+1)
A12: Q011 | B12: Accounting | C12: Financial Statements | D12: Balance Sheet | E12: Easy | F12: The basic accounting equation is: | G12: Assets = Liabilities − Equity | H12: Assets = Liabilities + Equity | I12: Assets + Liabilities = Equity | J12: Revenue = Expenses + Equity | K12: B | L12: Assets equal liabilities plus equity. | M12: Yes | N12: =IF(AND(M12="Yes",OR(QUIZ!$B$5="All Subjects",B12=QUIZ!$B$5),OR(QUIZ!$G$5="All Difficulties",E12=QUIZ!$G$5)),1,0) -> 0 | O12: =IF(N12=0,999999,MOD(IFERROR(VALUE(RIGHT(A12,3)),ROW())*7919+IF(N(QUIZ!$B$6)=0,1,QUIZ!$B$6)*104729+ROW()*IF(N(QUIZ!$B$6)=0,1,QUIZ!$B$6),999983)+ROW()/1000) -> 999999 | P12: =IF(N12=0,"",COUNTIFS($N$2:$N$510,1,$O$2:$O$510,"<"&O12)+1)
A13: Q012 | B13: Accounting | C13: Financial Statements | D13: Income Statement | E13: Medium | F13: Gross profit equals: | G13: Sales − operating expenses | H13: Sales − cost of goods sold | I13: Net income + tax | J13: Assets − liabilities | K13: B | L13: Gross profit is sales minus cost of goods sold. | M13: Yes | N13: =IF(AND(M13="Yes",OR(QUIZ!$B$5="All Subjects",B13=QUIZ!$B$5),OR(QUIZ!$G$5="All Difficulties",E13=QUIZ!$G$5)),1,0) -> 0 | O13: =IF(N13=0,999999,MOD(IFERROR(VALUE(RIGHT(A13,3)),ROW())*7919+IF(N(QUIZ!$B$6)=0,1,QUIZ!$B$6)*104729+ROW()*IF(N(QUIZ!$B$6)=0,1,QUIZ!$B$6),999983)+ROW()/1000) -> 999999 | P13: =IF(N13=0,"",COUNTIFS($N$2:$N$510,1,$O$2:$O$510,"<"&O13)+1)
... A50: Q049 | B50: Excel | C50: Pivot Tables | D50: Summaries | E50: Hard | F50: A PivotTable calculated field: | G50: Changes the workbook file type | H50: Creates a formula from other pivot fields | I50: Deletes the pivot cache | J50: Requires a macro | K50: B | L50: A calculated field is a formula built from fields already in the pivot cache. | M50: Yes | N50: =IF(AND(M50="Yes",OR(QUIZ!$B$5="All Subjects",B50=QUIZ!$B$5),OR(QUIZ!$G$5="All Difficulties",E50=QUIZ!$G$5)),1,0) -> 0 | O50: =IF(N50=0,999999,MOD(IFERROR(VALUE(RIGHT(A50,3)),ROW())*7919+IF(N(QUIZ!$B$6)=0,1,QUIZ!$B$6)*104729+ROW()*IF(N(QUIZ!$B$6)=0,1,QUIZ!$B$6),999983)+ROW()/1000) -> 999999 | P50: =IF(N50=0,"",COUNTIFS($N$2:$N$510,1,$O$2:$O$510,"<"&O50)+1)
A51: MATH001 | B51: Mathematics | C51: Calculus | D51: Integration | E51: Medium | F51: Using substitution, evaluate the indefinite integral of 2x(x^2+1)^3. | G51: (x^2+1)^4 / 4 + C | H51: (x^2+1)^3 / 3 + C | I51: 2(x^2+1)^4 + C | J51: x^2(x^2+1)^4 + C | K51: A | L51: Let u = x^2+1, so du = 2x dx. The integral is u^4/4 + C. | M51: Yes | N51: =IF(AND(M51="Yes",OR(QUIZ!$B$5="All Subjects",B51=QUIZ!$B$5),OR(QUIZ!$G$5="All Difficulties",E51=QUIZ!$G$5)),1,0) -> 1 | O51: =IF(N51=0,999999,MOD(IFERROR(VALUE(RIGHT(A51,3)),ROW())*7919+IF(N(QUIZ!$B$6)=0,1,QUIZ!$B$6)*104729+ROW()*IF(N(QUIZ!$B$6)=0,1,QUIZ!$B$6),999983)+ROW()/1000) -> 112699.05 | P51: =IF(N51=0,"",COUNTIFS($N$2:$N$500,1,$O$2:$O$500,"<"&O51)+1) -> 1
A52: MATH002 | B52: Mathematics | C52: Calculus | D52: Integration | E52: Medium | F52: Using substitution, evaluate the indefinite integral of 2x e^(x^2). | G52: e^(x^2) + C | H52: 2e^(x^2) + C | I52: x e^(x^2) + C | J52: e^(2x) + C | K52: A | L52: Let u = x^2, so du = 2x dx. The integral is e^u + C = e^(x^2) + C. | M52: Yes | N52: =IF(AND(M52="Yes",OR(QUIZ!$B$5="All Subjects",B52=QUIZ!$B$5),OR(QUIZ!$G$5="All Difficulties",E52=QUIZ!$G$5)),1,0) -> 1 | O52: =IF(N52=0,999999,MOD(IFERROR(VALUE(RIGHT(A52,3)),ROW())*7919+IF(N(QUIZ!$B$6)=0,1,QUIZ!$B$6)*104729+ROW()*IF(N(QUIZ!$B$6)=0,1,QUIZ!$B$6),999983)+ROW()/1000) -> 120619.05 | P52: =IF(N52=0,"",COUNTIFS($N$2:$N$500,1,$O$2:$O$500,"<"&O52)+1) -> 3
A53: MATH003 | B53: Mathematics | C53: Calculus | D53: Integration | E53: Medium | F53: Evaluate the definite integral of 2x from 0 to 1. | G53: 1 | H53: 2 | I53: 0 | J53: 1/2 | K53: A | L53: The antiderivative is x^2. From 0 to 1 this is 1 - 0 = 1. | M53: Yes | N53: =IF(AND(M53="Yes",OR(QUIZ!$B$5="All Subjects",B53=QUIZ!$B$5),OR(QUIZ!$G$5="All Difficulties",E53=QUIZ!$G$5)),1,0) -> 1 | O53: =IF(N53=0,999999,MOD(IFERROR(VALUE(RIGHT(A53,3)),ROW())*7919+IF(N(QUIZ!$B$6)=0,1,QUIZ!$B$6)*104729+ROW()*IF(N(QUIZ!$B$6)=0,1,QUIZ!$B$6),999983)+ROW()/1000) -> 128539.05 | P53: =IF(N53=0,"",COUNTIFS($N$2:$N$500,1,$O$2:$O$500,"<"&O53)+1) -> 4
A54: MATH004 | B54: Mathematics | C54: Calculus | D54: Integration | E54: Medium | F54: Evaluate the definite integral of 3x^2 from 0 to 2. | G54: 8 | H54: 12 | I54: 4 | J54: 6 | K54: A | L54: The antiderivative is x^3. At 2 this is 8, and at 0 it is 0. | M54: Yes | N54: =IF(AND(M54="Yes",OR(QUIZ!$B$5="All Subjects",B54=QUIZ!$B$5),OR(QUIZ!$G$5="All Difficulties",E54=QUIZ!$G$5)),1,0) -> 1 | O54: =IF(N54=0,999999,MOD(IFERROR(VALUE(RIGHT(A54,3)),ROW())*7919+IF(N(QUIZ!$B$6)=0,1,QUIZ!$B$6)*104729+ROW()*IF(N(QUIZ!$B$6)=0,1,QUIZ!$B$6),999983)+ROW()/1000) -> 136459.05 | P54: =IF(N54=0,"",COUNTIFS($N$2:$N$500,1,$O$2:$O$500,"<"&O54)+1) -> 6
A55: MATH005 | B55: Mathematics | C55: Calculus | D55: Integration | E55: Medium | F55: Using substitution, evaluate the indefinite integral of 2x/(x^2+1). | G55: ln|x^2+1| + C | H55: 2 ln|x^2+1| + C | I55: ln|2x| + C | J55: arctan(x^2) + C | K55: A | L55: Let u = x^2+1, so du = 2x dx. The integral is ln|u| + C. | M55: Yes | N55: =IF(AND(M55="Yes",OR(QUIZ!$B$5="All Subjects",B55=QUIZ!$B$5),OR(QUIZ!$G$5="All Difficulties",E55=QUIZ!$G$5)),1,0) -> 1 | O55: =IF(N55=0,999999,MOD(IFERROR(VALUE(RIGHT(A55,3)),ROW())*7919+IF(N(QUIZ!$B$6)=0,1,QUIZ!$B$6)*104729+ROW()*IF(N(QUIZ!$B$6)=0,1,QUIZ!$B$6),999983)+ROW()/1000) -> 144379.05 | P55: =IF(N55=0,"",COUNTIFS($N$2:$N$500,1,$O$2:$O$500,"<"&O55)+1) -> 7
A56: MATH006 | B56: Mathematics | C56: Calculus | D56: Integration | E56: Medium | F56: Evaluate the definite integral of 1/x from 1 to e. | G56: 1 | H56: e | I56: 0 | J56: e-1 | K56: A | L56: The antiderivative is ln|x|. ln(e) - ln(1) = 1 - 0 = 1. | M56: Yes | N56: =IF(AND(M56="Yes",OR(QUIZ!$B$5="All Subjects",B56=QUIZ!$B$5),OR(QUIZ!$G$5="All Difficulties",E56=QUIZ!$G$5)),1,0) -> 1 | O56: =IF(N56=0,999999,MOD(IFERROR(VALUE(RIGHT(A56,3)),ROW())*7919+IF(N(QUIZ!$B$6)=0,1,QUIZ!$B$6)*104729+ROW()*IF(N(QUIZ!$B$6)=0,1,QUIZ!$B$6),999983)+ROW()/1000) -> 152299.06 | P56: =IF(N56=0,"",COUNTIFS($N$2:$N$500,1,$O$2:$O$500,"<"&O56)+1) -> 9
A57: MATH007 | B57: Mathematics | C57: Calculus | D57: Integration | E57: Medium | F57: Using the substitution u = sin(x), evaluate the indefinite integral of sin(x)cos(x). | G57: (1/2) sin^2(x) + C | H57: sin^2(x) + C | I57: cos^2(x) + C | J57: negative cos(x) + C | K57: A | L57: du = cos(x) dx, so the integral is u^2/2 + C = (1/2) sin^2(x) + C. | M57: Yes | N57: =IF(AND(M57="Yes",OR(QUIZ!$B$5="All Subjects",B57=QUIZ!$B$5),OR(QUIZ!$G$5="All Difficulties",E57=QUIZ!$G$5)),1,0) -> 1 | O57: =IF(N57=0,999999,MOD(IFERROR(VALUE(RIGHT(A57,3)),ROW())*7919+IF(N(QUIZ!$B$6)=0,1,QUIZ!$B$6)*104729+ROW()*IF(N(QUIZ!$B$6)=0,1,QUIZ!$B$6),999983)+ROW()/1000) -> 160219.06 | P57: =IF(N57=0,"",COUNTIFS($N$2:$N$500,1,$O$2:$O$500,"<"&O57)+1) -> 10
A58: MATH008 | B58: Mathematics | C58: Calculus | D58: Integration | E58: Medium | F58: Using substitution, evaluate the definite integral of 2x(x^2+1)^2 from 0 to 1. | G58: 7/3 | H58: 3 | I58: 1 | J58: 8/3 | K58: A | L58: Let u = x^2+1. Limits change from 1 to 2. The integral of u^2 is 8/3 - 1/3 = 7/3. | M58: Yes | N58: =IF(AND(M58="Yes",OR(QUIZ!$B$5="All Subjects",B58=QUIZ!$B$5),OR(QUIZ!$G$5="All Difficulties",E58=QUIZ!$G$5)),1,0) -> 1 | O58: =IF(N58=0,999999,MOD(IFERROR(VALUE(RIGHT(A58,3)),ROW())*7919+IF(N(QUIZ!$B$6)=0,1,QUIZ!$B$6)*104729+ROW()*IF(N(QUIZ!$B$6)=0,1,QUIZ!$B$6),999983)+ROW()/1000) -> 168139.06 | P58: =IF(N58=0,"",COUNTIFS($N$2:$N$500,1,$O$2:$O$500,"<"&O58)+1) -> 12
A59: MATH009 | B59: Mathematics | C59: Calculus | D59: Integration | E59: Medium | F59: Using substitution, evaluate the indefinite integral of x / sqrt(x^2+1). | G59: sqrt(x^2+1) + C | H59: 2 sqrt(x^2+1) + C | I59: ln|x^2+1| + C | J59: (x^2+1)^(3/2) / 3 + C | K59: A | L59: Let u = x^2+1, so du = 2x dx and x dx = du/2. The integral is sqrt(u) + C. | M59: Yes | N59: =IF(AND(M59="Yes",OR(QUIZ!$B$5="All Subjects",B59=QUIZ!$B$5),OR(QUIZ!$G$5="All Difficulties",E59=QUIZ!$G$5)),1,0) -> 1 | O59: =IF(N59=0,999999,MOD(IFERROR(VALUE(RIGHT(A59,3)),ROW())*7919+IF(N(QUIZ!$B$6)=0,1,QUIZ!$B$6)*104729+ROW()*IF(N(QUIZ!$B$6)=0,1,QUIZ!$B$6),999983)+ROW()/1000) -> 176059.06 | P59: =IF(N59=0,"",COUNTIFS($N$2:$N$500,1,$O$2:$O$500,"<"&O59)+1) -> 13
A60: MATH010 | B60: Mathematics | C60: Calculus | D60: Integration | E60: Medium | F60: Evaluate the definite integral of cos(x) from 0 to pi/2. | G60: 1 | H60: 0 | I60: pi/2 | J60: negative 1 | K60: A | L60: The antiderivative is sin(x). sin(pi/2) - sin(0) = 1 - 0 = 1. | M60: Yes | N60: =IF(AND(M60="Yes",OR(QUIZ!$B$5="All Subjects",B60=QUIZ!$B$5),OR(QUIZ!$G$5="All Difficulties",E60=QUIZ!$G$5)),1,0) -> 1 | O60: =IF(N60=0,999999,MOD(IFERROR(VALUE(RIGHT(A60,3)),ROW())*7919+IF(N(QUIZ!$B$6)=0,1,QUIZ!$B$6)*104729+ROW()*IF(N(QUIZ!$B$6)=0,1,QUIZ!$B$6),999983)+ROW()/1000) -> 183979.06 | P60: =IF(N60=0,"",COUNTIFS($N$2:$N$500,1,$O$2:$O$500,"<"&O60)+1) -> 14

Sheet AI QUESTION GENERATOR
A1: AI QUESTION GENERATOR | Z1: Subject | AA1: Prefix
A2: Build a copy-ready prompt, ask an AI for tab-separated rows, then paste those rows at the bottom of tblQuestions. | Z2: Mathematics | AA2: MATH
A3: SUBJECT | B3: Mathematics | Z3: Accounting | AA3: ACC
A4: TOPIC | B4: Calculus | Z4: Economics | AA4: ECO
A5: SUBTOPIC | B5: Integration | Z5: Excel | AA5: XLS
A6: DIFFICULTY | B6: Medium | Z6: PowerPoint | AA6: PPT
A7: NUMBER OF QUESTIONS | B7: 10 | Z7: Business Studies | AA7: BUS
A8: QUESTION TYPE | B8: Multiple Choice | Z8: English | AA8: ENG
A9: TARGET QUESTION IDs | B9: {=_xlfn.LET(_xlpm.pfx,IF(B3="","OTH",IFERROR(_xlfn.XLOOKUP(B3,$Z$2:$Z$10,$AA$2:$AA$10),UPPER(LEFT(SUBSTITUTE(B3," ",""),3)))), _xlpm.n,IFERROR(MAX(VALUE(RIGHT(_xlfn._xlws.FILTER(tblQuestions[Question ID],LEFT(tblQuestions[Question ID],LEN(_xlpm.pfx))=_xlpm.pfx),3))),0)+1, _xlpm.pfx&TEXT(_xlpm.n,"000")&" to "&_xlpm.pfx&TEXT(_xlpm.n+MAX(B7,1)-1,"000"))} -> MATH011 to MATH020 | D9: {=_xlfn.LET(_xlpm.pfx,IF(B3="","OTH",IFERROR(_xlfn.XLOOKUP(B3,$Z$2:$Z$10,$AA$2:$AA$10),UPPER(LEFT(SUBSTITUTE(B3," ",""),3)))), _xlpm.n,IFERROR(MAX(VALUE(RIGHT(_xlfn._xlws.FILTER(tblQuestions[Question ID],LEFT(tblQuestions[Question ID],LEN(_xlpm.pfx))=_xlpm.pfx),3))),0)+1, _xlpm.pfx&TEXT(_xlpm.n,"000"))} -> MATH011 | Z9: Computer Applications | AA9: CAP
A10: GENERATED QUESTION STYLE | B10: Exam Style | Z10: Other | AA10: OTH
A11: SPECIAL INSTRUCTIONS | B11: Focus on integration by substitution and basic definite integrals.
A16: GENERATED AI PROMPT
A17: {=_xlfn.CONCAT("Generate new questions for my Excel AI Study Assistant.",CHAR(10),CHAR(10),"Subject: ",B3,CHAR(10),"Topic: ",B4,CHAR(10),"Subtopic: ",B5,CHAR(10),"Difficulty: ",B6,CHAR(10),"Number of questions: ",B7,CHAR(10),"Question type: ",B8,CHAR(10),"Question style: ",B10,CHAR(10),"Starting Question ID: ",D9,CHAR(10),"Ending Question ID: ",_xlfn.LET(_xlpm.pfx,LEFT(D9,LEN(D9)-3), _xlpm.n, VALUE(RIGHT(D9,3)), _xlpm.pfx&TEXT(_xlpm.n+MAX(B7,1)-1,"000")),CHAR(10),"Special instructions: ",B11,CHAR(10),CHAR(10),"CRITICAL INSTRUCTIONS",CHAR(10),"1. Generate exactly the requested number of questions.",CHAR(10),"2. Every question must be multiple choice.",CHAR(10),"3. Every question must have exactly four options: A, B, C, and D.",CHAR(10),"4. Exactly ONE option must be correct.",CHAR(10),"5. Provide the correct answer.",CHAR(10),"6. Provide a concise explanation.",CHAR(10),"7. Questions must be factually accurate.",CHAR(10),"8. Questions must match the requested subject, topic, subtopic, and difficulty. If difficulty is Mixed, spread Easy, Medium, and Hard.",CHAR(10),"9. Do not create duplicate questions.",CHAR(10),"10. Do not create questions that are merely reworded versions of each other.",CHAR(10),"11. Use different concepts and calculations whenever possible.",CHAR(10),"12. Make incorrect options plausible rather than obviously wrong.",CHAR(10),"13. For numerical questions, independently calculate and verify the answer.",CHAR(10),"14. Do not include answers inside the question text.",CHAR(10),"15. Do not use question numbers such as Question 1 inside the question text.",CHAR(10),"16. Generate unique Question IDs, starting at ",D9," and increasing by 1.",CHAR(10),"17. Do not reuse Question IDs that already exist in QUESTION_BANK.",CHAR(10),"18. Keep explanations short but useful.",CHAR(10),"19. Do not include Markdown tables.",CHAR(10),"20. Do not include headings, introductions, explanations, or extra text around the data.",CHAR(10),"21. Return ONLY the data rows in the exact requested format.",CHAR(10),CHAR(10),"EXACT OUTPUT FORMAT",CHAR(10),"Return TAB-SEPARATED VALUES with exactly these columns, in this order:",CHAR(10),"Question ID, Subject, Topic, Subtopic, Difficulty, Question, Option A, Option B, Option C, Option D, Correct Answer, Explanation, Active",CHAR(10),"Correct Answer must be only A, B, C, or D. Set Active to Yes on every row.",CHAR(10),"Example (tabs, not spaces):",CHAR(10),D9,CHAR(9),B3,CHAR(9),B4,CHAR(9),B5,CHAR(9),IF(B6="Mixed","Medium",B6),CHAR(9),"What is the integral of 2x?",CHAR(9),"x^2 + C",CHAR(9),"2x^2 + C",CHAR(9),"x + C",CHAR(9),"2 + C",CHAR(9),"A",CHAR(9),"The integral of 2x is x^2 + C.",CHAR(9),"Yes",CHAR(10),CHAR(10),"Do NOT add Markdown tables, numbering, bullets, extra columns, blank rows, commentary, or code fences.",CHAR(10),"The rows will be pasted directly underneath the existing records in tblQuestions. Keep this exact column order:",CHAR(10),"A Question ID, B Subject, C Topic, D Subtopic, E Difficulty, F Question, G Option A, H Option B, I Option C, J Option D, K Correct Answer, L Explanation, M Active.",CHAR(10),CHAR(10),"If I provide an existing-question list after this prompt, compare against it and do not repeat or closely reword those questions.",CHAR(10),CHAR(10),"EXISTING QUESTION IDS",CHAR(10),_xlfn.TEXTJOIN(", ",TRUE,tblQuestions[Question ID]),CHAR(10),CHAR(10),"EXISTING QUESTIONS FOR THIS SUBJECT — do not repeat or closely reword these:",CHAR(10),IFERROR(_xlfn.TEXTJOIN(CHAR(10),TRUE,_xlfn._xlws.FILTER(tblQuestions[Question ID]&" | "&tblQuestions[Question],tblQuestions[Subject]=B3)),"None yet for this subject."))} -> Generate new questions for my Excel AI Study Assistant. Subject: Mathematics Topic: Calculus Subtopic: Integration Difficulty: Medium Number of questions: 10 Question type: Multiple Choice Question style: Exam Style Starting Question ID: MATH011 Ending Question ID: MATH020 Special instructions: Focus on integration by substitution and basic definite integrals. CRITICAL INSTRUCTIONS 1. Generate exactly the requested number of questions. 2. Every question must be multiple choice. 3. Every question must have exactly four options: A, B, C, and D. 4. Exactly ONE option must be correct. 5. Provide the correct answer. 6. Provide a concise explanation. 7. Questions must be factually accurate. 8. Questions must match the requested subject, topic, subtopic, and difficulty. If difficulty is Mixed, spread Easy, Medium, and Hard. 9. Do not create duplicate questions. 10. Do not create questions that are merely reworded versions of each other. 11. Use different concepts and calculations whenever possible. 12. Make incorrect options plausible rather than obviously wrong. 13. For numerical questions, independently calculate and verify the answer. 14. Do not include answers inside the question text. 15. Do not use question numbers such as Question 1 inside the question text. 16. Generate unique Question IDs, starting at MATH011 and increasing by 1. 17. Do not reuse Question IDs that already exist in QUESTION_BANK. 18. Keep explanations short but useful. 19. Do not include Markdown tables. 20. Do not include headings, introductions, explanations, or extra text around the data. 21. Return ONLY the data rows in the exact requested format. EXACT OUTPUT FORMAT Return TAB-SEPARATED VALUES with exactly these columns, in this order: Question ID, Subject, Topic, Subtopic, Difficulty, Question, Option A, Option B, Option C, Option D, Correct Answer, Explanation, Active Correct Answer must be only A, B, C, or D. Set Active to Yes on every row. Example (tabs, not spaces): MATH011 Mathematics Calculus Integration Medium What is the integral of 2x? x^2 + C 2x^2 + C x + C 2 + C A The integral of 2x is x^2 + C. Yes Do NOT add Markdown tables, numbering, bullets, extra columns, blank rows, commentary, or code fences. The rows will be pasted directly underneath the existing records in tblQuestions. Keep this exact column order: A Question ID, B Subject, C Topic, D Subtopic, E Difficulty, F Question, G Option A, H Option B, I Option C, J Option D, K Correct Answer, L Explanation, M Active. If I provide an existing-question list after this prompt, compare against it and do not repeat or closely reword those questions. EXISTING QUESTION IDS Q001, Q002, Q003, Q004, Q005, Q006, Q007, Q008, Q009, Q010, Q011, Q012, Q013, Q014, Q015, Q016, Q017, Q018, Q019, Q020, Q021, Q022, Q023, Q024, Q025, Q026, Q027, Q028, Q029, Q030, Q031, Q032, Q033, Q034, Q035, Q036, Q037, Q038, Q039, Q040, Q041, Q042, Q043, Q044, Q045, Q046, Q047, Q048, Q049, MATH001, MATH002, MATH003, MATH004, MATH005, MATH006, MATH007, MATH008, MATH009, MATH010 EXISTING QUESTIONS FOR THIS SUBJECT — do not repeat or closely reword these: Q001 | What is the derivative of x²? Q002 | What is the derivative of sin(x)? Q003 | What is the indefinite integral of 2x? Q004 | What is the indefinite integral of 1/x? Q005 | Solve 2x + 3 = 11. Q006 | What are the roots of x² − 5x + 6 = 0? Q007 | What is the mean of 2, 4, 6, and 8? Q008 | A fair coin is flipped twice. What is the probability of two heads? Q037 | What is 10% of 200? Q039 | What is 15% of 80? Q040 | The median of 3, 9, and 4 is: MATH001 | Using substitution, evaluate the indefinite integral of 2x(x^2+1)^3. MATH002 | Using substitution, evaluate the indefinite integral of 2x e^(x^2). MATH003 | Evaluate the definite integral of 2x from 0 to 1. MATH004 | Evaluate the definite integral of 3x^2 from 0 to 2. MATH005 | Using substitution, evaluate the indefinite integral of 2x/(x^2+1). MATH006 | Evaluate the definite integral of 1/x from 1 to e. MATH007 | Using the substitution u = sin(x), evaluate the indefinite integral of sin(x)cos(x). MATH008 | Using substitution, evaluate the definite integral of 2x(x^2+1)^2 from 0 to 1. MATH009 | Using substitution, evaluate the indefinite integral of x / sqrt(x^2+1). MATH010 | Evaluate the definite integral of cos(x) from 0 to pi/2.
A30: PASTE GENERATED QUESTIONS HERE
A31: Excel 2021 cannot import this automatically. 1) Fill the blue inputs. 2) Copy the GENERATED AI PROMPT. 3) Give it to Grok or another AI. 4) Copy the tab-separated rows. 5) Paste them directly under the last row of tblQuestions on QUESTION_BANK. The table and quiz pick up new Active = Yes rows. The grid below is only a staging check, not a second database.
A34: Question ID | B34: Subject | C34: Topic | D34: Subtopic | E34: Difficulty | F34: Question | G34: Option A | H34: Option B | I34: Option C | J34: Option D | K34: Correct Answer | L34: Explanation | M34: Active
A36: LATEST QUESTIONS IN QUESTION_BANK
A37: Question ID | B37: Subject | C37: Topic | D37: Difficulty | E37: Question | F37: Correct Answer
A38: {=IFERROR(INDEX(tblQuestions[Question ID],ROWS(tblQuestions[Question ID])-9),"")} -> MATH001 | B38: =IF(A38="","",_xlfn.XLOOKUP(A38,tblQuestions[Question ID],tblQuestions[Subject])) -> Mathematics | C38: =IF(A38="","",_xlfn.XLOOKUP(A38,tblQuestions[Question ID],tblQuestions[Topic])) -> Calculus | D38: =IF(A38="","",_xlfn.XLOOKUP(A38,tblQuestions[Question ID],tblQuestions[Difficulty])) -> Medium | E38: =IF(A38="","",_xlfn.XLOOKUP(A38,tblQuestions[Question ID],tblQuestions[Question])) -> Using substitution, evaluate the indefinite integral of 2x(x^2+1)^3. | F38: =IF(A38="","",_xlfn.XLOOKUP(A38,tblQuestions[Question ID],tblQuestions[Correct Answer])) -> A
A39: {=IFERROR(INDEX(tblQuestions[Question ID],ROWS(tblQuestions[Question ID])-8),"")} -> MATH002 | B39: =IF(A39="","",_xlfn.XLOOKUP(A39,tblQuestions[Question ID],tblQuestions[Subject])) -> Mathematics | C39: =IF(A39="","",_xlfn.XLOOKUP(A39,tblQuestions[Question ID],tblQuestions[Topic])) -> Calculus | D39: =IF(A39="","",_xlfn.XLOOKUP(A39,tblQuestions[Question ID],tblQuestions[Difficulty])) -> Medium | E39: =IF(A39="","",_xlfn.XLOOKUP(A39,tblQuestions[Question ID],tblQuestions[Question])) -> Using substitution, evaluate the indefinite integral of 2x e^(x^2). | F39: =IF(A39="","",_xlfn.XLOOKUP(A39,tblQuestions[Question ID],tblQuestions[Correct Answer])) -> A
A40: {=IFERROR(INDEX(tblQuestions[Question ID],ROWS(tblQuestions[Question ID])-7),"")} -> MATH003 | B40: =IF(A40="","",_xlfn.XLOOKUP(A40,tblQuestions[Question ID],tblQuestions[Subject])) -> Mathematics | C40: =IF(A40="","",_xlfn.XLOOKUP(A40,tblQuestions[Question ID],tblQuestions[Topic])) -> Calculus | D40: =IF(A40="","",_xlfn.XLOOKUP(A40,tblQuestions[Question ID],tblQuestions[Difficulty])) -> Medium | E40: =IF(A40="","",_xlfn.XLOOKUP(A40,tblQuestions[Question ID],tblQuestions[Question])) -> Evaluate the definite integral of 2x from 0 to 1. | F40: =IF(A40="","",_xlfn.XLOOKUP(A40,tblQuestions[Question ID],tblQuestions[Correct Answer])) -> A
A41: {=IFERROR(INDEX(tblQuestions[Question ID],ROWS(tblQuestions[Question ID])-6),"")} -> MATH004 | B41: =IF(A41="","",_xlfn.XLOOKUP(A41,tblQuestions[Question ID],tblQuestions[Subject])) -> Mathematics | C41: =IF(A41="","",_xlfn.XLOOKUP(A41,tblQuestions[Question ID],tblQuestions[Topic])) -> Calculus | D41: =IF(A41="","",_xlfn.XLOOKUP(A41,tblQuestions[Question ID],tblQuestions[Difficulty])) -> Medium | E41: =IF(A41="","",_xlfn.XLOOKUP(A41,tblQuestions[Question ID],tblQuestions[Question])) -> Evaluate the definite integral of 3x^2 from 0 to 2. | F41: =IF(A41="","",_xlfn.XLOOKUP(A41,tblQuestions[Question ID],tblQuestions[Correct Answer])) -> A
A42: {=IFERROR(INDEX(tblQuestions[Question ID],ROWS(tblQuestions[Question ID])-5),"")} -> MATH005 | B42: =IF(A42="","",_xlfn.XLOOKUP(A42,tblQuestions[Question ID],tblQuestions[Subject])) -> Mathematics | C42: =IF(A42="","",_xlfn.XLOOKUP(A42,tblQuestions[Question ID],tblQuestions[Topic])) -> Calculus | D42: =IF(A42="","",_xlfn.XLOOKUP(A42,tblQuestions[Question ID],tblQuestions[Difficulty])) -> Medium | E42: =IF(A42="","",_xlfn.XLOOKUP(A42,tblQuestions[Question ID],tblQuestions[Question])) -> Using substitution, evaluate the indefinite integral of 2x/(x^2+1). | F42: =IF(A42="","",_xlfn.XLOOKUP(A42,tblQuestions[Question ID],tblQuestions[Correct Answer])) -> A
A43: {=IFERROR(INDEX(tblQuestions[Question ID],ROWS(tblQuestions[Question ID])-4),"")} -> MATH006 | B43: =IF(A43="","",_xlfn.XLOOKUP(A43,tblQuestions[Question ID],tblQuestions[Subject])) -> Mathematics | C43: =IF(A43="","",_xlfn.XLOOKUP(A43,tblQuestions[Question ID],tblQuestions[Topic])) -> Calculus | D43: =IF(A43="","",_xlfn.XLOOKUP(A43,tblQuestions[Question ID],tblQuestions[Difficulty])) -> Medium | E43: =IF(A43="","",_xlfn.XLOOKUP(A43,tblQuestions[Question ID],tblQuestions[Question])) -> Evaluate the definite integral of 1/x from 1 to e. | F43: =IF(A43="","",_xlfn.XLOOKUP(A43,tblQuestions[Question ID],tblQuestions[Correct Answer])) -> A
A44: {=IFERROR(INDEX(tblQuestions[Question ID],ROWS(tblQuestions[Question ID])-3),"")} -> MATH007 | B44: =IF(A44="","",_xlfn.XLOOKUP(A44,tblQuestions[Question ID],tblQuestions[Subject])) -> Mathematics | C44: =IF(A44="","",_xlfn.XLOOKUP(A44,tblQuestions[Question ID],tblQuestions[Topic])) -> Calculus | D44: =IF(A44="","",_xlfn.XLOOKUP(A44,tblQuestions[Question ID],tblQuestions[Difficulty])) -> Medium | E44: =IF(A44="","",_xlfn.XLOOKUP(A44,tblQuestions[Question ID],tblQuestions[Question])) -> Using the substitution u = sin(x), evaluate the indefinite integral of sin(x)cos(x). | F44: =IF(A44="","",_xlfn.XLOOKUP(A44,tblQuestions[Question ID],tblQuestions[Correct Answer])) -> A
A45: {=IFERROR(INDEX(tblQuestions[Question ID],ROWS(tblQuestions[Question ID])-2),"")} -> MATH008 | B45: =IF(A45="","",_xlfn.XLOOKUP(A45,tblQuestions[Question ID],tblQuestions[Subject])) -> Mathematics | C45: =IF(A45="","",_xlfn.XLOOKUP(A45,tblQuestions[Question ID],tblQuestions[Topic])) -> Calculus | D45: =IF(A45="","",_xlfn.XLOOKUP(A45,tblQuestions[Question ID],tblQuestions[Difficulty])) -> Medium | E45: =IF(A45="","",_xlfn.XLOOKUP(A45,tblQuestions[Question ID],tblQuestions[Question])) -> Using substitution, evaluate the definite integral of 2x(x^2+1)^2 from 0 to 1. | F45: =IF(A45="","",_xlfn.XLOOKUP(A45,tblQuestions[Question ID],tblQuestions[Correct Answer])) -> A
A46: {=IFERROR(INDEX(tblQuestions[Question ID],ROWS(tblQuestions[Question ID])-1),"")} -> MATH009 | B46: =IF(A46="","",_xlfn.XLOOKUP(A46,tblQuestions[Question ID],tblQuestions[Subject])) -> Mathematics | C46: =IF(A46="","",_xlfn.XLOOKUP(A46,tblQuestions[Question ID],tblQuestions[Topic])) -> Calculus | D46: =IF(A46="","",_xlfn.XLOOKUP(A46,tblQuestions[Question ID],tblQuestions[Difficulty])) -> Medium | E46: =IF(A46="","",_xlfn.XLOOKUP(A46,tblQuestions[Question ID],tblQuestions[Question])) -> Using substitution, evaluate the indefinite integral of x / sqrt(x^2+1). | F46: =IF(A46="","",_xlfn.XLOOKUP(A46,tblQuestions[Question ID],tblQuestions[Correct Answer])) -> A
A47: {=IFERROR(INDEX(tblQuestions[Question ID],ROWS(tblQuestions[Question ID])-0),"")} -> MATH010 | B47: =IF(A47="","",_xlfn.XLOOKUP(A47,tblQuestions[Question ID],tblQuestions[Subject])) -> Mathematics | C47: =IF(A47="","",_xlfn.XLOOKUP(A47,tblQuestions[Question ID],tblQuestions[Topic])) -> Calculus | D47: =IF(A47="","",_xlfn.XLOOKUP(A47,tblQuestions[Question ID],tblQuestions[Difficulty])) -> Medium | E47: =IF(A47="","",_xlfn.XLOOKUP(A47,tblQuestions[Question ID],tblQuestions[Question])) -> Evaluate the definite integral of cos(x) from 0 to pi/2. | F47: =IF(A47="","",_xlfn.XLOOKUP(A47,tblQuestions[Question ID],tblQuestions[Correct Answer])) -> A
A48: ← HOME | C48: QUESTION BANK

Sheet RESULTS
A1: QUIZ RESULTS
A2: Review the current quiz, see the score, and find the weakest subtopic.
A3: ← HOME | E3: → PROGRESS
A5: SUMMARY | F5: PERFORMANCE
A6: Subject | B6: =IF(QUIZ!AA3=0,"-",QUIZ!B5) -> Mathematics | F6: =IF(QUIZ!O6=0,"Take a quiz to see a performance message.",IF(QUIZ!O12>=0.9,"Excellent! You have a strong understanding of this material.",IF(QUIZ!O12>=0.75,"Very good! A little more practice can make your performance even stronger.",IF(QUIZ!O12>=0.5,"Good attempt. Review the weaker areas and try another quiz.","Focus on the fundamentals and review the weak topics before attempting another quiz.")))) -> Focus on the fundamentals and review the weak topics before attempting another quiz.
A7: Difficulty | B7: =IF(QUIZ!AA3=0,"-",QUIZ!G5) -> Medium
A8: Questions | B8: =QUIZ!O6 -> 10
A9: Correct | B9: =QUIZ!O8 -> 0 | AA9: =IF(QUIZ!AA9="","",_xlfn.XLOOKUP(QUIZ!AA9,tblQuestions[Question ID],tblQuestions[Subtopic])) -> Integration
A10: Incorrect | B10: =QUIZ!O9 -> 0 | AA10: =IF(QUIZ!AA10="","",_xlfn.XLOOKUP(QUIZ!AA10,tblQuestions[Question ID],tblQuestions[Subtopic])) -> Derivatives
A11: Not Answered | B11: =QUIZ!O10 -> 10 | AA11: =IF(QUIZ!AA11="","",_xlfn.XLOOKUP(QUIZ!AA11,tblQuestions[Question ID],tblQuestions[Subtopic])) -> Integration
A12: Score | B12: =QUIZ!O11 -> 0 / 10 | AA12: =IF(QUIZ!AA12="","",_xlfn.XLOOKUP(QUIZ!AA12,tblQuestions[Question ID],tblQuestions[Subtopic])) -> Integration
A13: Accuracy | B13: =IF(QUIZ!O6=0,"-",QUIZ!O12) -> 0 | AA13: =IF(QUIZ!AA13="","",_xlfn.XLOOKUP(QUIZ!AA13,tblQuestions[Question ID],tblQuestions[Subtopic])) -> Integration
AA14: =IF(QUIZ!AA14="","",_xlfn.XLOOKUP(QUIZ!AA14,tblQuestions[Question ID],tblQuestions[Subtopic])) -> Integration
A15: WEAK TOPIC ANALYSIS | AA15: =IF(QUIZ!AA15="","",_xlfn.XLOOKUP(QUIZ!AA15,tblQuestions[Question ID],tblQuestions[Subtopic])) -> Integration
A16: Subtopic | B16: Questions | C16: Correct | D16: Accuracy | AA16: =IF(QUIZ!AA16="","",_xlfn.XLOOKUP(QUIZ!AA16,tblQuestions[Question ID],tblQuestions[Subtopic])) -> Quadratic Equations | AB16: {=IFERROR(_xlfn.UNIQUE(_xlfn._xlws.FILTER(AA9:AA28,AA9:AA28<>"")),"")} -> Integration
A17: {=IFERROR(IF(INDEX(_xlfn.ANCHORARRAY($AB$16),ROW()-16)="","",INDEX(_xlfn.ANCHORARRAY($AB$16),ROW()-16)),"")} -> Integration | B17: =IF(A17="","",COUNTIF($AA$9:$AA$28,A17)) -> 8 | C17: {=IF(A17="","",SUMPRODUCT(($AA$9:$AA$28=A17)*(QUIZ!$K$9:$K$28="CORRECT")))} -> 0 | D17: =IF(OR(A17="",B17=0),"",C17/B17) -> 0 | AA17: =IF(QUIZ!AA17="","",_xlfn.XLOOKUP(QUIZ!AA17,tblQuestions[Question ID],tblQuestions[Subtopic])) -> Integration | AB17: Derivatives
A18: {=IFERROR(IF(INDEX(_xlfn.ANCHORARRAY($AB$16),ROW()-16)="","",INDEX(_xlfn.ANCHORARRAY($AB$16),ROW()-16)),"")} -> Derivatives | B18: =IF(A18="","",COUNTIF($AA$9:$AA$28,A18)) -> 1 | C18: {=IF(A18="","",SUMPRODUCT(($AA$9:$AA$28=A18)*(QUIZ!$K$9:$K$28="CORRECT")))} -> 0 | D18: =IF(OR(A18="",B18=0),"",C18/B18) -> 0 | AA18: =IF(QUIZ!AA18="","",_xlfn.XLOOKUP(QUIZ!AA18,tblQuestions[Question ID],tblQuestions[Subtopic])) -> Integration | AB18: Quadratic Equations
A19: {=IFERROR(IF(INDEX(_xlfn.ANCHORARRAY($AB$16),ROW()-16)="","",INDEX(_xlfn.ANCHORARRAY($AB$16),ROW()-16)),"")} -> Quadratic Equations | B19: =IF(A19="","",COUNTIF($AA$9:$AA$28,A19)) -> 1 | C19: {=IF(A19="","",SUMPRODUCT(($AA$9:$AA$28=A19)*(QUIZ!$K$9:$K$28="CORRECT")))} -> 0 | D19: =IF(OR(A19="",B19=0),"",C19/B19) -> 0 | AA19: =IF(QUIZ!AA19="","",_xlfn.XLOOKUP(QUIZ!AA19,tblQuestions[Question ID],tblQuestions[Subtopic]))
A20: {=IFERROR(IF(INDEX(_xlfn.ANCHORARRAY($AB$16),ROW()-16)="","",INDEX(_xlfn.ANCHORARRAY($AB$16),ROW()-16)),"")} | B20: =IF(A20="","",COUNTIF($AA$9:$AA$28,A20)) | C20: {=IF(A20="","",SUMPRODUCT(($AA$9:$AA$28=A20)*(QUIZ!$K$9:$K$28="CORRECT")))} | D20: =IF(OR(A20="",B20=0),"",C20/B20) | AA20: =IF(QUIZ!AA20="","",_xlfn.XLOOKUP(QUIZ!AA20,tblQuestions[Question ID],tblQuestions[Subtopic]))
A21: {=IFERROR(IF(INDEX(_xlfn.ANCHORARRAY($AB$16),ROW()-16)="","",INDEX(_xlfn.ANCHORARRAY($AB$16),ROW()-16)),"")} | B21: =IF(A21="","",COUNTIF($AA$9:$AA$28,A21)) | C21: {=IF(A21="","",SUMPRODUCT(($AA$9:$AA$28=A21)*(QUIZ!$K$9:$K$28="CORRECT")))} | D21: =IF(OR(A21="",B21=0),"",C21/B21) | AA21: =IF(QUIZ!AA21="","",_xlfn.XLOOKUP(QUIZ!AA21,tblQuestions[Question ID],tblQuestions[Subtopic]))
A22: {=IFERROR(IF(INDEX(_xlfn.ANCHORARRAY($AB$16),ROW()-16)="","",INDEX(_xlfn.ANCHORARRAY($AB$16),ROW()-16)),"")} | B22: =IF(A22="","",COUNTIF($AA$9:$AA$28,A22)) | C22: {=IF(A22="","",SUMPRODUCT(($AA$9:$AA$28=A22)*(QUIZ!$K$9:$K$28="CORRECT")))} | D22: =IF(OR(A22="",B22=0),"",C22/B22) | AA22: =IF(QUIZ!AA22="","",_xlfn.XLOOKUP(QUIZ!AA22,tblQuestions[Question ID],tblQuestions[Subtopic]))
A23: {=IFERROR(IF(INDEX(_xlfn.ANCHORARRAY($AB$16),ROW()-16)="","",INDEX(_xlfn.ANCHORARRAY($AB$16),ROW()-16)),"")} | B23: =IF(A23="","",COUNTIF($AA$9:$AA$28,A23)) | C23: {=IF(A23="","",SUMPRODUCT(($AA$9:$AA$28=A23)*(QUIZ!$K$9:$K$28="CORRECT")))} | D23: =IF(OR(A23="",B23=0),"",C23/B23) | AA23: =IF(QUIZ!AA23="","",_xlfn.XLOOKUP(QUIZ!AA23,tblQuestions[Question ID],tblQuestions[Subtopic]))
A24: {=IFERROR(IF(INDEX(_xlfn.ANCHORARRAY($AB$16),ROW()-16)="","",INDEX(_xlfn.ANCHORARRAY($AB$16),ROW()-16)),"")} | B24: =IF(A24="","",COUNTIF($AA$9:$AA$28,A24)) | C24: {=IF(A24="","",SUMPRODUCT(($AA$9:$AA$28=A24)*(QUIZ!$K$9:$K$28="CORRECT")))} | D24: =IF(OR(A24="",B24=0),"",C24/B24) | AA24: =IF(QUIZ!AA24="","",_xlfn.XLOOKUP(QUIZ!AA24,tblQuestions[Question ID],tblQuestions[Subtopic]))
A25: {=IFERROR(IF(INDEX(_xlfn.ANCHORARRAY($AB$16),ROW()-16)="","",INDEX(_xlfn.ANCHORARRAY($AB$16),ROW()-16)),"")} | B25: =IF(A25="","",COUNTIF($AA$9:$AA$28,A25)) | C25: {=IF(A25="","",SUMPRODUCT(($AA$9:$AA$28=A25)*(QUIZ!$K$9:$K$28="CORRECT")))} | D25: =IF(OR(A25="",B25=0),"",C25/B25) | AA25: =IF(QUIZ!AA25="","",_xlfn.XLOOKUP(QUIZ!AA25,tblQuestions[Question ID],tblQuestions[Subtopic]))
A26: {=IFERROR(IF(INDEX(_xlfn.ANCHORARRAY($AB$16),ROW()-16)="","",INDEX(_xlfn.ANCHORARRAY($AB$16),ROW()-16)),"")} | B26: =IF(A26="","",COUNTIF($AA$9:$AA$28,A26)) | C26: {=IF(A26="","",SUMPRODUCT(($AA$9:$AA$28=A26)*(QUIZ!$K$9:$K$28="CORRECT")))} | D26: =IF(OR(A26="",B26=0),"",C26/B26) | AA26: =IF(QUIZ!AA26="","",_xlfn.XLOOKUP(QUIZ!AA26,tblQuestions[Question ID],tblQuestions[Subtopic]))
A27: {=IFERROR(IF(INDEX(_xlfn.ANCHORARRAY($AB$16),ROW()-16)="","",INDEX(_xlfn.ANCHORARRAY($AB$16),ROW()-16)),"")} | B27: =IF(A27="","",COUNTIF($AA$9:$AA$28,A27)) | C27: {=IF(A27="","",SUMPRODUCT(($AA$9:$AA$28=A27)*(QUIZ!$K$9:$K$28="CORRECT")))} | D27: =IF(OR(A27="",B27=0),"",C27/B27) | AA27: =IF(QUIZ!AA27="","",_xlfn.XLOOKUP(QUIZ!AA27,tblQuestions[Question ID],tblQuestions[Subtopic]))
A28: {=IFERROR(IF(INDEX(_xlfn.ANCHORARRAY($AB$16),ROW()-16)="","",INDEX(_xlfn.ANCHORARRAY($AB$16),ROW()-16)),"")} | B28: =IF(A28="","",COUNTIF($AA$9:$AA$28,A28)) | C28: {=IF(A28="","",SUMPRODUCT(($AA$9:$AA$28=A28)*(QUIZ!$K$9:$K$28="CORRECT")))} | D28: =IF(OR(A28="",B28=0),"",C28/B28) | AA28: =IF(QUIZ!AA28="","",_xlfn.XLOOKUP(QUIZ!AA28,tblQuestions[Question ID],tblQuestions[Subtopic]))
A30: Weakest Area | B30: {=IFERROR(INDEX(_xlfn.SORTBY(_xlfn._xlws.FILTER(A17:A28,B17:B28>0),_xlfn._xlws.FILTER(D17:D28,B17:B28>0),1),1),"-")} -> Integration
A31: =IF(B30="-","Recommended: Complete a quiz to receive a study recommendation.",IFERROR(IF(INDEX(D17:D28,MATCH(B30,A17:A28,0))<0.5,"Recommended: Review "&B30&" before taking another quiz.",IF(INDEX(D17:D28,MATCH(B30,A17:A28,0))<0.75,"Recommended: Practice more questions from "&B30&".",IF(INDEX(D17:D28,MATCH(B30,A17:A28,0))<0.9,"Recommended: Continue practicing "&B30&" to improve consistency.","Recommended: Move to a harder difficulty."))),"Recommended: Complete a quiz to receive a study recommendation.")) -> Recommended: Review Integration before taking another quiz.
A34: QUESTION REVIEW
A35: Question | B35: Your Answer | C35: Correct Answer | D35: Result | E35: Explanation
A36: =IF(QUIZ!AA9="","",QUIZ!B9) -> Using substitution, evaluate the indefinite integral of 2x(x^2+1)^3. A. (x^2+1)^4 / 4 + C B. (x^2+1)^3 / 3 + C C. 2(x^2+1)^4 + C D. x^2(x^2+1)^4 + C | B36: =IF(QUIZ!AA9="","",IF(QUIZ!I9="","-",QUIZ!I9)) -> - | C36: =IF(QUIZ!AA9="","",_xlfn.XLOOKUP(QUIZ!AA9,tblQuestions[Question ID],tblQuestions[Correct Answer])) -> A | D36: =IF(QUIZ!AA9="","",QUIZ!K9) -> NOT ANSWERED | E36: =IF(QUIZ!AA9="","",_xlfn.XLOOKUP(QUIZ!AA9,tblQuestions[Question ID],tblQuestions[Explanation])) -> Let u = x^2+1, so du = 2x dx. The integral is u^4/4 + C.
A37: =IF(QUIZ!AA10="","",QUIZ!B10) -> What is the derivative of sin(x)? A. -cos(x) B. sin(x) C. cos(x) D. tan(x) | B37: =IF(QUIZ!AA10="","",IF(QUIZ!I10="","-",QUIZ!I10)) -> - | C37: =IF(QUIZ!AA10="","",_xlfn.XLOOKUP(QUIZ!AA10,tblQuestions[Question ID],tblQuestions[Correct Answer])) -> C | D37: =IF(QUIZ!AA10="","",QUIZ!K10) -> NOT ANSWERED | E37: =IF(QUIZ!AA10="","",_xlfn.XLOOKUP(QUIZ!AA10,tblQuestions[Question ID],tblQuestions[Explanation])) -> The derivative of sin(x) is cos(x).
A38: =IF(QUIZ!AA11="","",QUIZ!B11) -> Using substitution, evaluate the indefinite integral of 2x e^(x^2). A. e^(x^2) + C B. 2e^(x^2) + C C. x e^(x^2) + C D. e^(2x) + C | B38: =IF(QUIZ!AA11="","",IF(QUIZ!I11="","-",QUIZ!I11)) -> - | C38: =IF(QUIZ!AA11="","",_xlfn.XLOOKUP(QUIZ!AA11,tblQuestions[Question ID],tblQuestions[Correct Answer])) -> A | D38: =IF(QUIZ!AA11="","",QUIZ!K11) -> NOT ANSWERED | E38: =IF(QUIZ!AA11="","",_xlfn.XLOOKUP(QUIZ!AA11,tblQuestions[Question ID],tblQuestions[Explanation])) -> Let u = x^2, so du = 2x dx. The integral is e^u + C = e^(x^2) + C.
A39: =IF(QUIZ!AA12="","",QUIZ!B12) -> Evaluate the definite integral of 2x from 0 to 1. A. 1 B. 2 C. 0 D. 1/2 | B39: =IF(QUIZ!AA12="","",IF(QUIZ!I12="","-",QUIZ!I12)) -> - | C39: =IF(QUIZ!AA12="","",_xlfn.XLOOKUP(QUIZ!AA12,tblQuestions[Question ID],tblQuestions[Correct Answer])) -> A | D39: =IF(QUIZ!AA12="","",QUIZ!K12) -> NOT ANSWERED | E39: =IF(QUIZ!AA12="","",_xlfn.XLOOKUP(QUIZ!AA12,tblQuestions[Question ID],tblQuestions[Explanation])) -> The antiderivative is x^2. From 0 to 1 this is 1 - 0 = 1.
A40: =IF(QUIZ!AA13="","",QUIZ!B13) -> What is the indefinite integral of 1/x? A. x + C B. 1/x² + C C. ln|x| + C D. e^x + C | B40: =IF(QUIZ!AA13="","",IF(QUIZ!I13="","-",QUIZ!I13)) -> - | C40: =IF(QUIZ!AA13="","",_xlfn.XLOOKUP(QUIZ!AA13,tblQuestions[Question ID],tblQuestions[Correct Answer])) -> C | D40: =IF(QUIZ!AA13="","",QUIZ!K13) -> NOT ANSWERED | E40: =IF(QUIZ!AA13="","",_xlfn.XLOOKUP(QUIZ!AA13,tblQuestions[Question ID],tblQuestions[Explanation])) -> The integral of 1/x is the natural log of the absolute value of x, plus C.
A41: =IF(QUIZ!AA14="","",QUIZ!B14) -> Evaluate the definite integral of 3x^2 from 0 to 2. A. 8 B. 12 C. 4 D. 6 | B41: =IF(QUIZ!AA14="","",IF(QUIZ!I14="","-",QUIZ!I14)) -> - | C41: =IF(QUIZ!AA14="","",_xlfn.XLOOKUP(QUIZ!AA14,tblQuestions[Question ID],tblQuestions[Correct Answer])) -> A | D41: =IF(QUIZ!AA14="","",QUIZ!K14) -> NOT ANSWERED | E41: =IF(QUIZ!AA14="","",_xlfn.XLOOKUP(QUIZ!AA14,tblQuestions[Question ID],tblQuestions[Explanation])) -> The antiderivative is x^3. At 2 this is 8, and at 0 it is 0.
A42: =IF(QUIZ!AA15="","",QUIZ!B15) -> Using substitution, evaluate the indefinite integral of 2x/(x^2+1). A. ln|x^2+1| + C B. 2 ln|x^2+1| + C C. ln|2x| + C D. arctan(x^2) + C | B42: =IF(QUIZ!AA15="","",IF(QUIZ!I15="","-",QUIZ!I15)) -> - | C42: =IF(QUIZ!AA15="","",_xlfn.XLOOKUP(QUIZ!AA15,tblQuestions[Question ID],tblQuestions[Correct Answer])) -> A | D42: =IF(QUIZ!AA15="","",QUIZ!K15) -> NOT ANSWERED | E42: =IF(QUIZ!AA15="","",_xlfn.XLOOKUP(QUIZ!AA15,tblQuestions[Question ID],tblQuestions[Explanation])) -> Let u = x^2+1, so du = 2x dx. The integral is ln|u| + C.
A43: =IF(QUIZ!AA16="","",QUIZ!B16) -> What are the roots of x² − 5x + 6 = 0? A. 1 and 6 B. 2 and 3 C. −2 and −3 D. 5 and 6 | B43: =IF(QUIZ!AA16="","",IF(QUIZ!I16="","-",QUIZ!I16)) -> - | C43: =IF(QUIZ!AA16="","",_xlfn.XLOOKUP(QUIZ!AA16,tblQuestions[Question ID],tblQuestions[Correct Answer])) -> B | D43: =IF(QUIZ!AA16="","",QUIZ!K16) -> NOT ANSWERED | E43: =IF(QUIZ!AA16="","",_xlfn.XLOOKUP(QUIZ!AA16,tblQuestions[Question ID],tblQuestions[Explanation])) -> The quadratic factors as (x − 2)(x − 3) = 0.
A44: =IF(QUIZ!AA17="","",QUIZ!B17) -> Evaluate the definite integral of 1/x from 1 to e. A. 1 B. e C. 0 D. e-1 | B44: =IF(QUIZ!AA17="","",IF(QUIZ!I17="","-",QUIZ!I17)) -> - | C44: =IF(QUIZ!AA17="","",_xlfn.XLOOKUP(QUIZ!AA17,tblQuestions[Question ID],tblQuestions[Correct Answer])) -> A | D44: =IF(QUIZ!AA17="","",QUIZ!K17) -> NOT ANSWERED | E44: =IF(QUIZ!AA17="","",_xlfn.XLOOKUP(QUIZ!AA17,tblQuestions[Question ID],tblQuestions[Explanation])) -> The antiderivative is ln|x|. ln(e) - ln(1) = 1 - 0 = 1.
A45: =IF(QUIZ!AA18="","",QUIZ!B18) -> Using the substitution u = sin(x), evaluate the indefinite integral of sin(x)cos(x). A. (1/2) sin^2(x) + C B. sin^2(x) + C C. cos^2(x) + C D. negative cos(x) + C | B45: =IF(QUIZ!AA18="","",IF(QUIZ!I18="","-",QUIZ!I18)) -> - | C45: =IF(QUIZ!AA18="","",_xlfn.XLOOKUP(QUIZ!AA18,tblQuestions[Question ID],tblQuestions[Correct Answer])) -> A | D45: =IF(QUIZ!AA18="","",QUIZ!K18) -> NOT ANSWERED | E45: =IF(QUIZ!AA18="","",_xlfn.XLOOKUP(QUIZ!AA18,tblQuestions[Question ID],tblQuestions[Explanation])) -> du = cos(x) dx, so the integral is u^2/2 + C = (1/2) sin^2(x) + C.
A46: =IF(QUIZ!AA19="","",QUIZ!B19) | B46: =IF(QUIZ!AA19="","",IF(QUIZ!I19="","-",QUIZ!I19)) | C46: =IF(QUIZ!AA19="","",_xlfn.XLOOKUP(QUIZ!AA19,tblQuestions[Question ID],tblQuestions[Correct Answer])) | D46: =IF(QUIZ!AA19="","",QUIZ!K19) | E46: =IF(QUIZ!AA19="","",_xlfn.XLOOKUP(QUIZ!AA19,tblQuestions[Question ID],tblQuestions[Explanation]))
A47: =IF(QUIZ!AA20="","",QUIZ!B20) | B47: =IF(QUIZ!AA20="","",IF(QUIZ!I20="","-",QUIZ!I20)) | C47: =IF(QUIZ!AA20="","",_xlfn.XLOOKUP(QUIZ!AA20,tblQuestions[Question ID],tblQuestions[Correct Answer])) | D47: =IF(QUIZ!AA20="","",QUIZ!K20) | E47: =IF(QUIZ!AA20="","",_xlfn.XLOOKUP(QUIZ!AA20,tblQuestions[Question ID],tblQuestions[Explanation]))
... A55: =IF(QUIZ!AA28="","",QUIZ!B28) | B55: =IF(QUIZ!AA28="","",IF(QUIZ!I28="","-",QUIZ!I28)) | C55: =IF(QUIZ!AA28="","",_xlfn.XLOOKUP(QUIZ!AA28,tblQuestions[Question ID],tblQuestions[Correct Answer])) | D55: =IF(QUIZ!AA28="","",QUIZ!K28) | E55: =IF(QUIZ!AA28="","",_xlfn.XLOOKUP(QUIZ!AA28,tblQuestions[Question ID],tblQuestions[Explanation]))
A57: ADD CURRENT RESULT TO HISTORY
A58: Excel 2021 cannot append history by itself. Copy row 61, open PROGRESS, and Paste Values into the next blank row of tblHistory. Sample history rows can be overwritten.
A60: Attempt ID | B60: Date | C60: Subject | D60: Difficulty | E60: Questions | F60: Correct | G60: Incorrect | H60: Accuracy | I60: Score
A61: ="A"&TEXT(MAX(1,COUNTA(PROGRESS!A21:A200)),"000") -> A008 | B61: =TODAY() -> 46304 | C61: =IF(QUIZ!AA3=0,"",QUIZ!B5) -> Mathematics | D61: =IF(QUIZ!AA3=0,"",QUIZ!G5) -> Medium | E61: =QUIZ!O6 -> 10 | F61: =QUIZ!O8 -> 0 | G61: =QUIZ!O9 -> 0 | H61: =IF(QUIZ!O6=0,"",QUIZ!O12) -> 0 | I61: =IF(QUIZ!O6=0,"",QUIZ!O11) -> 0 / 10

Sheet WEAK TOPIC PRACTICE
A1: WEAK TOPIC PRACTICE
A2: Topics are scored from the current quiz. History stores subject only, so topic accuracy updates after each quiz. Copy the green rows into the log to keep a running record. | Z2: Mathematics | AA2: MATH
A3: ← HOME | C3: RESULTS | E3: AI QUESTION GENERATOR | Z3: Accounting | AA3: ACC
Z4: Economics | AA4: ECO
A5: YOUR WEAKEST TOPICS | Z5: Excel | AA5: XLS
A6: Subject | B6: Topic | C6: Subtopic | D6: Questions Attempted | E6: Correct | F6: Accuracy | G6: Performance | H6: Priority | Z6: PowerPoint | AA6: PPT
A7: =IF(C7="","",IFERROR(INDEX(tblQuestions[Subject],MATCH(C7,tblQuestions[Subtopic],0)),QUIZ!B5)) -> Mathematics | B7: =IF(C7="","",IFERROR(INDEX(tblQuestions[Topic],MATCH(C7,tblQuestions[Subtopic],0)),"")) -> Calculus | C7: =IF(RESULTS!A17="","",RESULTS!A17) -> Integration | D7: =IF(C7="","",RESULTS!B17) -> 8 | E7: =IF(C7="","",RESULTS!C17) -> 0 | F7: =IF(OR(C7="",D7=0),"",E7/D7) -> 0 | G7: =IF(C7="","",IF(D7<5,"Limited sample",IF(F7>=0.8,"Strong",IF(F7>=0.6,"Needs Practice","Weak")))) -> Weak | H7: =IF(C7="","",IF(D7<5,"Watch",IF(F7<0.5,"HIGH",IF(F7<0.7,"MEDIUM-HIGH",IF(F7<0.8,"MEDIUM","LOW"))))) -> HIGH | Z7: Business Studies | AA7: BUS
A8: =IF(C8="","",IFERROR(INDEX(tblQuestions[Subject],MATCH(C8,tblQuestions[Subtopic],0)),QUIZ!B5)) -> Mathematics | B8: =IF(C8="","",IFERROR(INDEX(tblQuestions[Topic],MATCH(C8,tblQuestions[Subtopic],0)),"")) -> Calculus | C8: =IF(RESULTS!A18="","",RESULTS!A18) -> Derivatives | D8: =IF(C8="","",RESULTS!B18) -> 1 | E8: =IF(C8="","",RESULTS!C18) -> 0 | F8: =IF(OR(C8="",D8=0),"",E8/D8) -> 0 | G8: =IF(C8="","",IF(D8<5,"Limited sample",IF(F8>=0.8,"Strong",IF(F8>=0.6,"Needs Practice","Weak")))) -> Limited sample | H8: =IF(C8="","",IF(D8<5,"Watch",IF(F8<0.5,"HIGH",IF(F8<0.7,"MEDIUM-HIGH",IF(F8<0.8,"MEDIUM","LOW"))))) -> Watch | Z8: English | AA8: ENG
A9: =IF(C9="","",IFERROR(INDEX(tblQuestions[Subject],MATCH(C9,tblQuestions[Subtopic],0)),QUIZ!B5)) -> Mathematics | B9: =IF(C9="","",IFERROR(INDEX(tblQuestions[Topic],MATCH(C9,tblQuestions[Subtopic],0)),"")) -> Algebra | C9: =IF(RESULTS!A19="","",RESULTS!A19) -> Quadratic Equations | D9: =IF(C9="","",RESULTS!B19) -> 1 | E9: =IF(C9="","",RESULTS!C19) -> 0 | F9: =IF(OR(C9="",D9=0),"",E9/D9) -> 0 | G9: =IF(C9="","",IF(D9<5,"Limited sample",IF(F9>=0.8,"Strong",IF(F9>=0.6,"Needs Practice","Weak")))) -> Limited sample | H9: =IF(C9="","",IF(D9<5,"Watch",IF(F9<0.5,"HIGH",IF(F9<0.7,"MEDIUM-HIGH",IF(F9<0.8,"MEDIUM","LOW"))))) -> Watch | Z9: Computer Applications | AA9: CAP
A10: =IF(C10="","",IFERROR(INDEX(tblQuestions[Subject],MATCH(C10,tblQuestions[Subtopic],0)),QUIZ!B5)) | B10: =IF(C10="","",IFERROR(INDEX(tblQuestions[Topic],MATCH(C10,tblQuestions[Subtopic],0)),"")) | C10: =IF(RESULTS!A20="","",RESULTS!A20) | D10: =IF(C10="","",RESULTS!B20) | E10: =IF(C10="","",RESULTS!C20) | F10: =IF(OR(C10="",D10=0),"",E10/D10) | G10: =IF(C10="","",IF(D10<5,"Limited sample",IF(F10>=0.8,"Strong",IF(F10>=0.6,"Needs Practice","Weak")))) | H10: =IF(C10="","",IF(D10<5,"Watch",IF(F10<0.5,"HIGH",IF(F10<0.7,"MEDIUM-HIGH",IF(F10<0.8,"MEDIUM","LOW"))))) | Z10: Other | AA10: OTH
A11: =IF(C11="","",IFERROR(INDEX(tblQuestions[Subject],MATCH(C11,tblQuestions[Subtopic],0)),QUIZ!B5)) | B11: =IF(C11="","",IFERROR(INDEX(tblQuestions[Topic],MATCH(C11,tblQuestions[Subtopic],0)),"")) | C11: =IF(RESULTS!A21="","",RESULTS!A21) | D11: =IF(C11="","",RESULTS!B21) | E11: =IF(C11="","",RESULTS!C21) | F11: =IF(OR(C11="",D11=0),"",E11/D11) | G11: =IF(C11="","",IF(D11<5,"Limited sample",IF(F11>=0.8,"Strong",IF(F11>=0.6,"Needs Practice","Weak")))) | H11: =IF(C11="","",IF(D11<5,"Watch",IF(F11<0.5,"HIGH",IF(F11<0.7,"MEDIUM-HIGH",IF(F11<0.8,"MEDIUM","LOW")))))
A12: =IF(C12="","",IFERROR(INDEX(tblQuestions[Subject],MATCH(C12,tblQuestions[Subtopic],0)),QUIZ!B5)) | B12: =IF(C12="","",IFERROR(INDEX(tblQuestions[Topic],MATCH(C12,tblQuestions[Subtopic],0)),"")) | C12: =IF(RESULTS!A22="","",RESULTS!A22) | D12: =IF(C12="","",RESULTS!B22) | E12: =IF(C12="","",RESULTS!C22) | F12: =IF(OR(C12="",D12=0),"",E12/D12) | G12: =IF(C12="","",IF(D12<5,"Limited sample",IF(F12>=0.8,"Strong",IF(F12>=0.6,"Needs Practice","Weak")))) | H12: =IF(C12="","",IF(D12<5,"Watch",IF(F12<0.5,"HIGH",IF(F12<0.7,"MEDIUM-HIGH",IF(F12<0.8,"MEDIUM","LOW")))))
A13: =IF(C13="","",IFERROR(INDEX(tblQuestions[Subject],MATCH(C13,tblQuestions[Subtopic],0)),QUIZ!B5)) | B13: =IF(C13="","",IFERROR(INDEX(tblQuestions[Topic],MATCH(C13,tblQuestions[Subtopic],0)),"")) | C13: =IF(RESULTS!A23="","",RESULTS!A23) | D13: =IF(C13="","",RESULTS!B23) | E13: =IF(C13="","",RESULTS!C23) | F13: =IF(OR(C13="",D13=0),"",E13/D13) | G13: =IF(C13="","",IF(D13<5,"Limited sample",IF(F13>=0.8,"Strong",IF(F13>=0.6,"Needs Practice","Weak")))) | H13: =IF(C13="","",IF(D13<5,"Watch",IF(F13<0.5,"HIGH",IF(F13<0.7,"MEDIUM-HIGH",IF(F13<0.8,"MEDIUM","LOW")))))
A14: =IF(C14="","",IFERROR(INDEX(tblQuestions[Subject],MATCH(C14,tblQuestions[Subtopic],0)),QUIZ!B5)) | B14: =IF(C14="","",IFERROR(INDEX(tblQuestions[Topic],MATCH(C14,tblQuestions[Subtopic],0)),"")) | C14: =IF(RESULTS!A24="","",RESULTS!A24) | D14: =IF(C14="","",RESULTS!B24) | E14: =IF(C14="","",RESULTS!C24) | F14: =IF(OR(C14="",D14=0),"",E14/D14) | G14: =IF(C14="","",IF(D14<5,"Limited sample",IF(F14>=0.8,"Strong",IF(F14>=0.6,"Needs Practice","Weak")))) | H14: =IF(C14="","",IF(D14<5,"Watch",IF(F14<0.5,"HIGH",IF(F14<0.7,"MEDIUM-HIGH",IF(F14<0.8,"MEDIUM","LOW")))))
A15: =IF(C15="","",IFERROR(INDEX(tblQuestions[Subject],MATCH(C15,tblQuestions[Subtopic],0)),QUIZ!B5)) | B15: =IF(C15="","",IFERROR(INDEX(tblQuestions[Topic],MATCH(C15,tblQuestions[Subtopic],0)),"")) | C15: =IF(RESULTS!A25="","",RESULTS!A25) | D15: =IF(C15="","",RESULTS!B25) | E15: =IF(C15="","",RESULTS!C25) | F15: =IF(OR(C15="",D15=0),"",E15/D15) | G15: =IF(C15="","",IF(D15<5,"Limited sample",IF(F15>=0.8,"Strong",IF(F15>=0.6,"Needs Practice","Weak")))) | H15: =IF(C15="","",IF(D15<5,"Watch",IF(F15<0.5,"HIGH",IF(F15<0.7,"MEDIUM-HIGH",IF(F15<0.8,"MEDIUM","LOW")))))
A16: =IF(C16="","",IFERROR(INDEX(tblQuestions[Subject],MATCH(C16,tblQuestions[Subtopic],0)),QUIZ!B5)) | B16: =IF(C16="","",IFERROR(INDEX(tblQuestions[Topic],MATCH(C16,tblQuestions[Subtopic],0)),"")) | C16: =IF(RESULTS!A26="","",RESULTS!A26) | D16: =IF(C16="","",RESULTS!B26) | E16: =IF(C16="","",RESULTS!C26) | F16: =IF(OR(C16="",D16=0),"",E16/D16) | G16: =IF(C16="","",IF(D16<5,"Limited sample",IF(F16>=0.8,"Strong",IF(F16>=0.6,"Needs Practice","Weak")))) | H16: =IF(C16="","",IF(D16<5,"Watch",IF(F16<0.5,"HIGH",IF(F16<0.7,"MEDIUM-HIGH",IF(F16<0.8,"MEDIUM","LOW")))))
A17: =IF(C17="","",IFERROR(INDEX(tblQuestions[Subject],MATCH(C17,tblQuestions[Subtopic],0)),QUIZ!B5)) | B17: =IF(C17="","",IFERROR(INDEX(tblQuestions[Topic],MATCH(C17,tblQuestions[Subtopic],0)),"")) | C17: =IF(RESULTS!A27="","",RESULTS!A27) | D17: =IF(C17="","",RESULTS!B27) | E17: =IF(C17="","",RESULTS!C27) | F17: =IF(OR(C17="",D17=0),"",E17/D17) | G17: =IF(C17="","",IF(D17<5,"Limited sample",IF(F17>=0.8,"Strong",IF(F17>=0.6,"Needs Practice","Weak")))) | H17: =IF(C17="","",IF(D17<5,"Watch",IF(F17<0.5,"HIGH",IF(F17<0.7,"MEDIUM-HIGH",IF(F17<0.8,"MEDIUM","LOW")))))
A18: =IF(C18="","",IFERROR(INDEX(tblQuestions[Subject],MATCH(C18,tblQuestions[Subtopic],0)),QUIZ!B5)) | B18: =IF(C18="","",IFERROR(INDEX(tblQuestions[Topic],MATCH(C18,tblQuestions[Subtopic],0)),"")) | C18: =IF(RESULTS!A28="","",RESULTS!A28) | D18: =IF(C18="","",RESULTS!B28) | E18: =IF(C18="","",RESULTS!C28) | F18: =IF(OR(C18="",D18=0),"",E18/D18) | G18: =IF(C18="","",IF(D18<5,"Limited sample",IF(F18>=0.8,"Strong",IF(F18>=0.6,"Needs Practice","Weak")))) | H18: =IF(C18="","",IF(D18<5,"Watch",IF(F18<0.5,"HIGH",IF(F18<0.7,"MEDIUM-HIGH",IF(F18<0.8,"MEDIUM","LOW")))))
A20: Focus subtopic | B20: {=IFERROR(INDEX(_xlfn.SORTBY(_xlfn._xlws.FILTER(C7:C18,(D7:D18>=5)*(C7:C18<>"")),_xlfn._xlws.FILTER(F7:F18,(D7:D18>=5)*(C7:C18<>""))),1),IFERROR(INDEX(_xlfn.SORTBY(_xlfn._xlws.FILTER(C7:C18,D7:D18>0),_xlfn._xlws.FILTER(F7:F18,D7:D18>0)),1),"-"))} -> Integration
A21: Focus topic | B21: =IF(B20="-","-",IFERROR(INDEX(B7:B18,MATCH(B20,C7:C18,0)),"-")) -> Calculus
A22: Accuracy | B22: =IF(B20="-","-",IFERROR(INDEX(F7:F18,MATCH(B20,C7:C18,0)),"-")) -> 0
A23: Why this topic | B23: =IF(B20="-","Answer a quiz to identify a weak topic.",IF(INDEX(D7:D18,MATCH(B20,C7:C18,0))<5,"Lowest accuracy so far, but fewer than 5 questions. Treat this as a watch item.","Lowest accuracy among topics with at least 5 attempted questions.")) -> Lowest accuracy among topics with at least 5 attempted questions.
A25: Practice questions | B25: 10
A26: Difficulty | B26: Medium
A27: Starting ID | B27: {=_xlfn.LET(_xlpm.subj,IF(B20="-","",IFERROR(INDEX(A7:A18,MATCH(B20,C7:C18,0)),"")), _xlpm.pfx,IF(_xlpm.subj="","OTH",IFERROR(_xlfn.XLOOKUP(_xlpm.subj,$Z$2:$Z$10,$AA$2:$AA$10),UPPER(LEFT(SUBSTITUTE(_xlpm.subj," ",""),3)))), _xlpm.n,IFERROR(MAX(VALUE(RIGHT(_xlfn._xlws.FILTER(tblQuestions[Question ID],LEFT(tblQuestions[Question ID],LEN(_xlpm.pfx))=_xlpm.pfx),3))),0)+1, _xlpm.pfx&TEXT(_xlpm.n,"000"))} -> MATH011
A29: PRACTICE PROMPT — copy this cell
A30: {=IF(B20="-","Answer the current quiz first. Weak topics appear after questions are scored.",_xlfn.CONCAT("Generate new questions for my Excel AI Study Assistant.",CHAR(10),CHAR(10),"WEAK TOPIC: ",B21," → ",B20,CHAR(10),"Subject: ",IFERROR(INDEX(A7:A18,MATCH(B20,C7:C18,0)),""),CHAR(10),"Topic: ",B21,CHAR(10),"Subtopic: ",B20,CHAR(10),"Current accuracy: ",TEXT(B22,"0.0%"),CHAR(10),"Difficulty: ",B26,CHAR(10),"Number of questions: ",B25,CHAR(10),"Starting Question ID: ",B27,CHAR(10),CHAR(10),"CRITICAL INSTRUCTIONS",CHAR(10),"1. Generate exactly ",B25," new multiple-choice questions on ",B20," only.",CHAR(10),"2. Every question needs exactly four options, A B C D, and exactly one correct answer.",CHAR(10),"3. Provide a short explanation. Keep questions factually accurate and at ",B26," difficulty.",CHAR(10),"4. Do not repeat or closely reword questions already in the bank for this subtopic.",CHAR(10),"5. Make incorrect options plausible. Verify any calculation independently.",CHAR(10),"6. Do not put the answer in the question text, and do not number the questions.",CHAR(10),"7. Use Question IDs starting at ",B27," and increasing by 1. Do not reuse an existing ID.",CHAR(10),"8. Set Active to Yes. Return ONLY tab-separated rows, no Markdown, headings, or commentary.",CHAR(10),CHAR(10),"Columns in order: Question ID, Subject, Topic, Subtopic, Difficulty, Question, Option A, Option B, Option C, Option D, Correct Answer, Explanation, Active",CHAR(10),CHAR(10),"EXISTING IDS: ",_xlfn.TEXTJOIN(", ",TRUE,tblQuestions[Question ID]),CHAR(10),CHAR(10),"EXISTING QUESTIONS ON THIS SUBTOPIC:",CHAR(10),IFERROR(_xlfn.TEXTJOIN(CHAR(10),TRUE,_xlfn._xlws.FILTER(tblQuestions[Question ID]&" | "&tblQuestions[Question],tblQuestions[Subtopic]=B20)),"None yet.")))} -> Generate new questions for my Excel AI Study Assistant. WEAK TOPIC: Calculus → Integration Subject: Mathematics Topic: Calculus Subtopic: Integration Current accuracy: 0.0% Difficulty: Medium Number of questions: 10 Starting Question ID: MATH011 CRITICAL INSTRUCTIONS 1. Generate exactly 10 new multiple-choice questions on Integration only. 2. Every question needs exactly four options, A B C D, and exactly one correct answer. 3. Provide a short explanation. Keep questions factually accurate and at Medium difficulty. 4. Do not repeat or closely reword questions already in the bank for this subtopic. 5. Make incorrect options plausible. Verify any calculation independently. 6. Do not put the answer in the question text, and do not number the questions. 7. Use Question IDs starting at MATH011 and increasing by 1. Do not reuse an existing ID. 8. Set Active to Yes. Return ONLY tab-separated rows, no Markdown, headings, or commentary. Columns in order: Question ID, Subject, Topic, Subtopic, Difficulty, Question, Option A, Option B, Option C, Option D, Correct Answer, Explanation, Active EXISTING IDS: Q001, Q002, Q003, Q004, Q005, Q006, Q007, Q008, Q009, Q010, Q011, Q012, Q013, Q014, Q015, Q016, Q017, Q018, Q019, Q020, Q021, Q022, Q023, Q024, Q025, Q026, Q027, Q028, Q029, Q030, Q031, Q032, Q033, Q034, Q035, Q036, Q037, Q038, Q039, Q040, Q041, Q042, Q043, Q044, Q045, Q046, Q047, Q048, Q049, MATH001, MATH002, MATH003, MATH004, MATH005, MATH006, MATH007, MATH008, MATH009, MATH010 EXISTING QUESTIONS ON THIS SUBTOPIC: Q003 | What is the indefinite integral of 2x? Q004 | What is the indefinite integral of 1/x? MATH001 | Using substitution, evaluate the indefinite integral of 2x(x^2+1)^3. MATH002 | Using substitution, evaluate the indefinite integral of 2x e^(x^2). MATH003 | Evaluate the definite integral of 2x from 0 to 1. MATH004 | Evaluate the definite integral of 3x^2 from 0 to 2. MATH005 | Using substitution, evaluate the indefinite integral of 2x/(x^2+1). MATH006 | Evaluate the definite integral of 1/x from 1 to e. MATH007 | Using the substitution u = sin(x), evaluate the indefinite integral of sin(x)cos(x). MATH008 | Using substitution, evaluate the definite integral of 2x(x^2+1)^2 from 0 to 1. MATH009 | Using substitution, evaluate the indefinite integral of x / sqrt(x^2+1). MATH010 | Evaluate the definite integral of cos(x) from 0 to pi/2.
A44: ADD CURRENT QUIZ TOPICS TO THE LOG
A45: Quiz history stores subject only, not topic. Copy these green rows and Paste Values under the log to build a running record. A topic is classified only after 5 attempted questions; fewer stay Watch.
A46: Subject | B46: Topic | C46: Subtopic | D46: Attempted | E46: Correct | F46: Accuracy | G46: Date
A47: =IF(C7="","",A7) -> Mathematics | B47: =IF(C7="","",B7) -> Calculus | C47: =IF(C7="","",C7) -> Integration | D47: =IF(C7="","",D7) -> 8 | E47: =IF(C7="","",E7) -> 0 | F47: =IF(C7="","",F7) -> 0 | G47: =IF(C7="","",TODAY()) -> 46304
A48: =IF(C8="","",A8) -> Mathematics | B48: =IF(C8="","",B8) -> Calculus | C48: =IF(C8="","",C8) -> Derivatives | D48: =IF(C8="","",D8) -> 1 | E48: =IF(C8="","",E8) -> 0 | F48: =IF(C8="","",F8) -> 0 | G48: =IF(C8="","",TODAY()) -> 46304
A49: =IF(C9="","",A9) -> Mathematics | B49: =IF(C9="","",B9) -> Algebra | C49: =IF(C9="","",C9) -> Quadratic Equations | D49: =IF(C9="","",D9) -> 1 | E49: =IF(C9="","",E9) -> 0 | F49: =IF(C9="","",F9) -> 0 | G49: =IF(C9="","",TODAY()) -> 46304
A50: =IF(C10="","",A10) | B50: =IF(C10="","",B10) | C50: =IF(C10="","",C10) | D50: =IF(C10="","",D10) | E50: =IF(C10="","",E10) | F50: =IF(C10="","",F10) | G50: =IF(C10="","",TODAY())
A51: =IF(C11="","",A11) | B51: =IF(C11="","",B11) | C51: =IF(C11="","",C11) | D51: =IF(C11="","",D11) | E51: =IF(C11="","",E11) | F51: =IF(C11="","",F11) | G51: =IF(C11="","",TODAY())
A52: =IF(C12="","",A12) | B52: =IF(C12="","",B12) | C52: =IF(C12="","",C12) | D52: =IF(C12="","",D12) | E52: =IF(C12="","",E12) | F52: =IF(C12="","",F12) | G52: =IF(C12="","",TODAY())
A53: =IF(C13="","",A13) | B53: =IF(C13="","",B13) | C53: =IF(C13="","",C13) | D53: =IF(C13="","",D13) | E53: =IF(C13="","",E13) | F53: =IF(C13="","",F13) | G53: =IF(C13="","",TODAY())
A54: =IF(C14="","",A14) | B54: =IF(C14="","",B14) | C54: =IF(C14="","",C14) | D54: =IF(C14="","",D14) | E54: =IF(C14="","",E14) | F54: =IF(C14="","",F14) | G54: =IF(C14="","",TODAY())
A57: Subject | B57: Topic | C57: Subtopic | D57: Attempted | E57: Correct | F57: Accuracy | G57: Date
A58: Paste rows above this line

Sheet PROGRESS
A1: STUDY PROGRESS
A2: Long-term performance from quiz history. Sample rows are included so the dashboard is ready to use.
A3: ← HOME | E3: → RESULTS
B4: Total Quizzes | D4: Total Questions | F4: Average Accuracy | H4: Best Accuracy | J4: Questions Correct | L4: Questions Incorrect
B5: =COUNTA(tblHistory[Attempt ID]) -> 6 | D5: =SUM(tblHistory[Questions]) -> 50 | F5: =IF(B5=0,"-",AVERAGE(tblHistory[Accuracy])) -> 0.71666667 | H5: =IF(B5=0,"-",MAX(tblHistory[Accuracy])) -> 1 | J5: =SUM(tblHistory[Correct]) -> 34 | L5: =SUM(tblHistory[Incorrect]) -> 16
A8: PERFORMANCE BY SUBJECT | G8: PERFORMANCE BY DIFFICULTY
A9: Subject | B9: Quizzes | C9: Questions | D9: Correct | E9: Accuracy | G9: Difficulty | H9: Attempts | I9: Accuracy
A10: Mathematics | B10: =COUNTIF(tblHistory[Subject],A10) -> 2 | C10: =SUMIF(tblHistory[Subject],A10,tblHistory[Questions]) -> 20 | D10: =SUMIF(tblHistory[Subject],A10,tblHistory[Correct]) -> 12 | E10: =IF(C10=0,"-",D10/C10) -> 0.6 | G10: Easy | H10: =COUNTIF(tblHistory[Difficulty],G10) -> 3 | I10: =IF(H10=0,"-",AVERAGEIF(tblHistory[Difficulty],G10,tblHistory[Accuracy])) -> 0.86666667
A11: Accounting | B11: =COUNTIF(tblHistory[Subject],A11) -> 1 | C11: =SUMIF(tblHistory[Subject],A11,tblHistory[Questions]) -> 10 | D11: =SUMIF(tblHistory[Subject],A11,tblHistory[Correct]) -> 6 | E11: =IF(C11=0,"-",D11/C11) -> 0.6 | G11: Medium | H11: =COUNTIF(tblHistory[Difficulty],G11) -> 2 | I11: =IF(H11=0,"-",AVERAGEIF(tblHistory[Difficulty],G11,tblHistory[Accuracy])) -> 0.65
A12: Economics | B12: =COUNTIF(tblHistory[Subject],A12) -> 1 | C12: =SUMIF(tblHistory[Subject],A12,tblHistory[Questions]) -> 5 | D12: =SUMIF(tblHistory[Subject],A12,tblHistory[Correct]) -> 4 | E12: =IF(C12=0,"-",D12/C12) -> 0.8 | G12: Hard | H12: =COUNTIF(tblHistory[Difficulty],G12) -> 1 | I12: =IF(H12=0,"-",AVERAGEIF(tblHistory[Difficulty],G12,tblHistory[Accuracy])) -> 0.4
A13: Excel | B13: =COUNTIF(tblHistory[Subject],A13) -> 1 | C13: =SUMIF(tblHistory[Subject],A13,tblHistory[Questions]) -> 10 | D13: =SUMIF(tblHistory[Subject],A13,tblHistory[Correct]) -> 7 | E13: =IF(C13=0,"-",D13/C13) -> 0.7
A14: PowerPoint | B14: =COUNTIF(tblHistory[Subject],A14) -> 1 | C14: =SUMIF(tblHistory[Subject],A14,tblHistory[Questions]) -> 5 | D14: =SUMIF(tblHistory[Subject],A14,tblHistory[Correct]) -> 5 | E14: =IF(C14=0,"-",D14/C14) -> 1
A16: STUDY INSIGHTS
A17: Strongest Subject | B17: {=IF(B5=0,"-",IFERROR(INDEX(A10:A14,MATCH(MAX(_xlfn._xlws.FILTER(E10:E14,B10:B14>0)),E10:E14,0)),"-"))} -> PowerPoint | D17: Best Score | E17: =H5 -> 1
A18: Weakest Subject | B18: {=IF(B5=0,"-",IFERROR(INDEX(A10:A14,MATCH(MIN(_xlfn._xlws.FILTER(E10:E14,B10:B14>0)),E10:E14,0)),"-"))} -> Mathematics | D18: Quizzes Completed | E18: =B5 -> 6
A19: Best Difficulty | B19: {=IF(B5=0,"-",IFERROR(INDEX(G10:G12,MATCH(MAX(_xlfn._xlws.FILTER(I10:I12,H10:H12>0)),I10:I12,0)),"-"))} -> Easy | D19: Questions Attempted | E19: =D5 -> 50
A20: Average Accuracy | B20: =F5 -> 0.71666667 | D20: Questions Incorrect | E20: =L5 -> 16
A23: QUIZ HISTORY — copy the green row on RESULTS and Paste Values into the next blank row
A24: Attempt ID | B24: Date | C24: Subject | D24: Difficulty | E24: Questions | F24: Correct | G24: Incorrect | H24: Accuracy | I24: Score
A25: A001 | B25: 2026-08-31T18:30:00.000Z | C25: Mathematics | D25: Easy | E25: 10 | F25: 8 | G25: 2 | H25: 0.8 | I25: 46244
A26: A002 | B26: 2026-09-07T18:30:00.000Z | C26: Accounting | D26: Medium | E26: 10 | F26: 6 | G26: 4 | H26: 0.6 | I26: 46183
A27: A003 | B27: 2026-09-14T18:30:00.000Z | C27: Economics | D27: Easy | E27: 5 | F27: 4 | G27: 1 | H27: 0.8 | I27: 46117
A28: A004 | B28: 2026-09-21T18:30:00.000Z | C28: Excel | D28: Medium | E28: 10 | F28: 7 | G28: 3 | H28: 0.7 | I28: 46213
A29: A005 | B29: 2026-09-28T18:30:00.000Z | C29: PowerPoint | D29: Easy | E29: 5 | F29: 5 | G29: 0 | H29: 1 | I29: 46147
A30: A006 | B30: 2026-10-01T18:30:00.000Z | C30: Mathematics | D30: Hard | E30: 10 | F30: 4 | G30: 6 | H30: 0.4 | I30: 46122

Sheet SETTINGS
A1: Subjects | C1: Difficulty | E1: Question Count | G1: Answer Options | I1: Generator Difficulty | K1: Generator Count | M1: Question Type | O1: Question Style
A2: All Subjects | C2: All Difficulties | E2: 5 | G2: A | I2: Easy | K2: 5 | M2: Multiple Choice | O2: Conceptual
A3: Mathematics | C3: Easy | E3: 10 | G3: B | I3: Medium | K3: 10 | M3: Mixed | O3: Calculation
A4: Accounting | C4: Medium | E4: 15 | G4: C | I4: Hard | K4: 20 | O4: Exam Style
A5: Economics | C5: Hard | E5: 20 | G5: D | I5: Mixed | K5: 30 | O5: Mixed
A6: Excel | K6: 50
A7: PowerPoint
A8: Business Studies
A9: English
A10: Computer Applications
A11: Other
A13: How these lists are used
A14: These lists feed the dropdowns on the QUIZ sheet and the AI QUESTION GENERATOR. Subject, Difficulty, and Question Count control which active questions are drawn. Answer Options (A-D) are the only values a student can enter. Generator lists on the right are used only when building an AI prompt. Only rows with Active = Yes are eligible for a quiz.
A17: lstSubjects = A2:A11 lstDifficulty = C2:C5 lstCount = E2:E5 lstAnswers = G2:G5
